Workbook

Sheet Sociedades
A1: Sociedad | B1: País
A2: TRAN | B2: Colombia
A3: ISA | B3: Colombia
A4: ITCH | B4: Chile
A5: CEYA
A6: CABA | B6: Colombia
A7: RPAE
A8: CTMP | B8: Perú
A9: REPD | B9: Perú
A10: ISAP | B10: Perú

Sheet Clase
A1: Sociedad | B1: Clase | C1: Descripción Clase
A2: ITCH | B2: 3A050200 | C2: Terrenos Rurales
A3: ITCH | B3: 3A400100 | C3: Edificios
A4: ITCH | B4: 3A400201 | C4: Leasing Financiero - Edificaciones
A5: ITCH | B5: 3A400202 | C5: Leasing Financiero - Edificaciones Relacion
A6: ITCH | B6: 3A451210 | C6: Equipos de Subestación Nueva Estruc 40 Años
A7: ITCH | B7: 3A451211 | C7: Equipos de Subestación Nueva Estruc 38 Años
A8: ITCH | B8: 3A451212 | C8: Equipos de Subestación Nueva Estruc 32 Años
A9: ITCH | B9: 3A451213 | C9: Equipos de Subestación Nueva Estruc 30 Años
A10: ITCH | B10: 3A451214 | C10: Equipos de Subestación Nueva Estruc 27 Años
A11: ITCH | B11: 3A451215 | C11: Equipos de Subestación Nueva Estruc 25 Años
A12: ITCH | B12: 3A451216 | C12: Equipos de Subestación Nueva Estruc 20 Años
... A292: CABA | B292: RC900210 | C292: Seguro - Seguros proyectos

Sheet Criterio 
A1: Sociedad | B1: Criterio 1 | C1: Asignación Criterio de Clasificación 1 | D1: Criterio 2 | E1: Asignación Criterio de Clasificación 2 | F1: Criterio 3 | G1: Asignación Criterio de Clasificación 3 | H1: Criterio 4 | I1: Asignación Criterio de Clasificación 4 | J1: Criterio 5 | K1: Asignación Criterio de Clasificación 5
A2: ITCH | F2: IC01 | G2: LT 2X500 KV Carrdones-Polpaico | J2: ICA10000 | K2: ACTIVOS ADMIN CORP
A3: ITCH | F3: IC02 | G3: Nueva Linea encuentro lagunas | J3: ICO10000 | K3: ACTIVOS ADMIN OYM
A4: ITCH | F4: IC03 | G4: Obra de ampliación tendido seg | J4: ICO20000 | K4: ACTIVOS EN ALMACEN
A5: ITCH | F5: IC04 | G5: Banco de autotransformadores D | J5: P001L001 | K5: Cardones-Maitencillo500kV-Conexiones220k
A6: ITCH | F6: IC05 | G6: Ampliación barras 500 kv SE NU | J6: P001L002 | K6: Maitencillo-PanDeAzucar500kV-Conexiones2
A7: ITCH | F7: IC06 | G7: Diagonal 3 y 4 220kv NMAI NPAN | J7: P001L003 | K7: PanDeAzucar-Polpaico500kV-Conexiones220k
A8: ITCH | F8: IC07 | G8: Bco autotransormador N1 DS373 | J8: P001S001 | K8: SE Nueva Cardones 500/220kV
A9: ITCH | F9: IC08 | G9: CS POLP Y STATCOM NPAN 500kv | J9: P001S002 | K9: AmpliaciónSECardonesExistente220kV
A10: ITCH | F10: IC09 | G10: Mando sincronizado atr ncar | J10: P001S003 | K10: SE Nueva Maitencillo 500/220kV
A11: ITCH | F11: IC11 | G11: Aumento Capacidad LT220 kV MAI- NMAI | J11: P001S004 | K11: AmpliaciónSEMaitencilloExistente220kV
A12: ITCH | F12: IC12 | G12: Ampliación Subestación NPAZ | J12: P001S005 | K12: SE Nueva Pan de Azúcar 500/220 kV
A13: ITCH | F13: ICA1 | G13: ACTIVOS ADMIN CORP | J13: P001S006 | K13: AmpliaciónSEPanDeAzucarExistente220kV
... A15: ITCH | F15: ICO2 | G15: ACTIVOS EN ALMACEN | J15: P002L004 | K15: Encuentro-Lagunas 2X220 kV 1Circuito
A16: ITCH | J16: P002S008 | K16: AmpliacionSE_LagunasExistente220kV
A17: ITCH | J17: P002S009 | K17: AmpliacionSE_EncuentroExistente220kV
A18: ITCH | J18: P003L004 | K18: 2do C Encuentro-Lagunas 2X220 kV
A19: ITCH | J19: P003S008 | K19: 2do C AmpliacionSE_Lagunas220kV
A20: ITCH | J20: P003S009 | K20: 2do C AmpliacionSE_Encuentro220kV
A21: ITCH | J21: P004S001 | K21: ATRs SE Nueva Cardones 500/220kV
A22: ITCH | J22: P004S003 | K22: ATRs SE Nueva Maitencillo 500/220kV
A23: ITCH | J23: P004S005 | K23: ATRs SE Nueva Pan de Azúcar 500/220 kV
A24: ITCH | J24: P005S001 | K24: Ampliación Barras 500 kV SE Nueva Cardones
A25: ITCH | J25: P007S011 | K25: ATR1 DS373 SE Nueva Maitencillo 500/220Kv
A26: ITCH | J26: P008S012 | K26: CS POPL Y STATCOM NPAN 500KV
A27: ITCH | J27: P009S013 | K27: Mando sincronizado ATR
... A30: ITCH | J30: ICO20000 | K30: ACTIVOS EN ALMACEN
A31: TRAN | F31: IC01 | G31: LT 2X500 KV Carrdones Polpaico | J31: ICA10000 | K31: ACTIVOS ADMIN CORP
A32: TRAN | F32: IC02 | G32: Nueva Linea encuentro lagunas | J32: ICO10000 | K32: ACTIVOS ADMIN OYM
A33: TRAN | F33: IC03 | G33: Obra de ampliación tendido seg | J33: ICO20000 | K33: ACTIVOS EN ALMACEN
A34: TRAN | F34: IC04 | G34: Banco de autotransformadores D | J34: P001L001 | K34: Cardones Maitencillo500kV Conexiones220k
A35: TRAN | F35: IC05 | G35: Ampliación barras 500 kv SE NU | J35: P001L002 | K35: Maitencillo Pan DeAzucar500kV Conexiones2
A36: TRAN | F36: IC06 | G36: Diagonal 3 y 4 220kv NMAI NPAN | J36: P001L003 | K36: PanDeAzucar Polpaico500kV Conexiones220k
A37: TRAN | F37: IC07 | G37: Bco autotransormador N1 DS373 | J37: P001S001 | K37: SE Nueva Cardones 500/220kV
A38: TRAN | F38: IC08 | G38: CS POLP Y STATCOM NPAN 500kv | J38: P001S002 | K38: AmpliaciónSECardonesExistente220kV
A39: TRAN | F39: IC09 | G39: Mando sincronizado atr ncar | J39: P001S003 | K39: SE Nueva Maitencillo 500/220kV
A40: TRAN | F40: IC11 | G40: Aumento Capacidad LT220 kV MAI NMAI | J40: P001S004 | K40: AmpliaciónSEMaitencilloExistente220kV
A41: TRAN | F41: IC12 | G41: Ampliación Subestación NPAZ | J41: P001S005 | K41: SE Nueva Pan de Azúcar 500/220 kV
A42: TRAN | F42: ICA1 | G42: ACTIVOS ADMIN CORP | J42: P001S006 | K42: AmpliaciónSEPanDeAzucarExistente220kV
... A44: TRAN | F44: ICO2 | G44: ACTIVOS EN ALMACEN | J44: P002L004 | K44: Encuentro Lagunas 2X220 kV 1Circuito
A45: TRAN | J45: P002S008 | K45: AmpliacionSE_LagunasExistente220kV
A46: TRAN | J46: P002S009 | K46: AmpliacionSE_EncuentroExistente220kV
A47: TRAN | J47: P003L004 | K47: 2do C Encuentro Lagunas 2X220 Kv
A48: TRAN | J48: P003S008 | K48: 2do C AmpliacionSE_Lagunas220kV
A49: TRAN | J49: P003S009 | K49: 2do C AmpliacionSE_Encuentro220kV
A50: TRAN | J50: P004S001 | K50: ATRs SE Nueva Cardones 500/220kV
A51: TRAN | J51: P004S003 | K51: ATRs SE Nueva Maitencillo 500/220kV
A52: TRAN | J52: P004S005 | K52: ATRs SE Nueva Pan de Azúcar 500/220 kV
A53: TRAN | J53: P005S001 | K53: Ampliación Barras 500 kV SE Nueva Cardones
A54: TRAN | J54: P007S011 | K54: ATR1 DS373 SE Nueva Maitencillo 500/220Kv
A55: TRAN | J55: P008S012 | K55: CS POPL Y STATCOM NPAN 500KV
A56: TRAN | J56: P009S013 | K56: Mando sincronizado ATR
... A59: TRAN | J59: ICO20000 | K59: ACTIVOS EN ALMACEN
A60: ISA | F60: IC01 | G60: LT 2X500 KV Carrdones Polpaico | J60: ICA10000 | K60: ACTIVOS ADMIN CORP
A61: ISA | F61: IC02 | G61: Nueva Linea encuentro lagunas | J61: ICO10000 | K61: ACTIVOS ADMIN OYM
A62: ISA | F62: IC03 | G62: Obra de ampliación tendido seg | J62: ICO20000 | K62: ACTIVOS EN ALMACEN
A63: ISA | F63: IC04 | G63: Banco de autotransformadores D | J63: P001L001 | K63: Cardones Maitencillo500kV Conexiones220k
A64: ISA | F64: IC05 | G64: Ampliación barras 500 kv SE NU | J64: P001L002 | K64: Maitencillo Pan DeAzucar500kV Conexiones2
A65: ISA | F65: IC06 | G65: Diagonal 3 y 4 220kv NMAI NPAN | J65: P001L003 | K65: PanDeAzucar Polpaico500kV Conexiones220k
A66: ISA | F66: IC07 | G66: Bco autotransormador N1 DS373 | J66: P001S001 | K66: SE Nueva Cardones 500/220kV
A67: ISA | F67: IC08 | G67: CS POLP Y STATCOM NPAN 500kv | J67: P001S002 | K67: AmpliaciónSECardonesExistente220kV
A68: ISA | F68: IC09 | G68: Mando sincronizado atr ncar | J68: P001S003 | K68: SE Nueva Maitencillo 500/220kV
A69: ISA | F69: IC11 | G69: Aumento Capacidad LT220 kV MAI NMAI | J69: P001S004 | K69: AmpliaciónSEMaitencilloExistente220kV
A70: ISA | F70: IC12 | G70: Ampliación Subestación NPAZ | J70: P001S005 | K70: SE Nueva Pan de Azúcar 500/220 kV
A71: ISA | F71: ICA1 | G71: ACTIVOS ADMIN CORP | J71: P001S006 | K71: AmpliaciónSEPanDeAzucarExistente220kV
... A73: ISA | F73: ICO2 | G73: ACTIVOS EN ALMACEN | J73: P002L004 | K73: Encuentro Lagunas 2X220 kV 1Circuito
A74: ISA | J74: P002S008 | K74: AmpliacionSE_LagunasExistente220kV
A75: ISA | J75: P002S009 | K75: AmpliacionSE_EncuentroExistente220kV
A76: ISA | J76: P003L004 | K76: 2do C Encuentro Lagunas 2X220 Kv
A77: ISA | J77: P003S008 | K77: 2do C AmpliacionSE_Lagunas220kV
A78: ISA | J78: P003S009 | K78: 2do C AmpliacionSE_Encuentro220kV
A79: ISA | J79: P004S001 | K79: ATRs SE Nueva Cardones 500/220kV
A80: ISA | J80: P004S003 | K80: ATRs SE Nueva Maitencillo 500/220kV
A81: ISA | J81: P004S005 | K81: ATRs SE Nueva Pan de Azúcar 500/220 kV
A82: ISA | J82: P005S001 | K82: Ampliación Barras 500 kV SE Nueva Cardones
A83: ISA | J83: P007S011 | K83: ATR1 DS373 SE Nueva Maitencillo 500/220Kv
A84: ISA | J84: P008S012 | K84: CS POPL Y STATCOM NPAN 500KV
A85: ISA | J85: P009S013 | K85: Mando sincronizado ATR
... A88: ISA | J88: ICO20000 | K88: ACTIVOS EN ALMACEN
A89: CABA | D89: 001 | E89: Puerto Colombia | F89: 001 | G89: Policia Nacional | H89: RC01 | I89: Activo Reversible
A90: CABA | D90: 002 | E90: Galapa | F90: 002 | G90: CCO Galapa | H90: RC02 | I90: Consorcio via al mar
A91: CABA | D91: 003 | E91: Juan Mina | F91: 003 | G91: Ambiental | H91: RC03 | I91: Activos No Reversibles
A92: CABA | D92: 004 | E92: Marahuaco | F92: 004 | G92: Área de Servicio
A93: CABA | D93: 005 | E93: Papiros | F93: 005 | G93: Bascula Galapa
A94: CABA | D94: 006 | E94: Túnel Crespo | F94: 006 | G94: Bascula Juan Mina
A95: CABA | D95: 007 | E95: Barranquilla | F95: 007 | G95: Bascula Papiros
A96: CABA | F96: 008 | G96: BC Empresarial
A97: CABA | F97: 009 | G97: Gerencia
A98: CABA | F98: 010 | G98: Gestión EPC
A99: CABA | F99: 011 | G99: Mantenimiento
A100: CABA | F100: 012 | G100: Operación
A101: CABA | F101: 013 | G101: Peaje Galapa
A102: CABA | F102: 014 | G102: Peaje Juan Mina
A103: CABA | F103: 015 | G103: Peaje Marahuaco
A104: CABA | F104: 016 | G104: Peaje Puerto Colombia
A105: CABA | F105: 017 | G105: SST
A106: CABA | F106: 018 | G106: Gerencia Tecnica
A107: CABA | F107: 019 | G107: Túnel Crespo
A108: CABA | F108: 020 | G108: Peaje Papiros

Sheet Ceco
A1: Sociedad | B1: CECO | C1: Responsable | D1: Nombre CECO
A2: ITCH | B2: 10000 | C2: 10000 | D2: GERENCIA GENERAL
A3: ITCH | B3: 10001 | C3: 10001 | D3: ABASTECIMIENTO
A4: ITCH | B4: 10002 | C4: 10002 | D4: ADMINISTRACIÓN
A5: ITCH | B5: 10003 | C5: 10003 | D5: TALENTO ORGANIZ
A6: ITCH | B6: 10004 | C6: 10004 | D6: LEGAL
A7: ITCH | B7: 10005 | C7: 10005 | D7: TI
A8: ITCH | B8: 10006 | C8: 10006 | D8: NUEVOS NEGOCIOS
A9: ITCH | B9: 10007 | C9: 10007 | D9: SST
A10: ITCH | B10: 10008 | C10: 10008 | D10: ESTRATEGIA
A11: ITCH | B11: 10009 | C11: 10009 | D11: ALMACÉN
A12: ITCH | B12: 12000 | C12: 12000 | D12: INCE NUEVOS NEGOCIOS
A13: ITCH | B13: 13000 | C13: 13000 | D13: INNO PROYECTO KILA
... A34: ITCH | B34: 70000 | C34: 70000 | D34: AUDITORÍA INTERNA
A35: ITCH | B35: ANALAG2201 | C35: ANALAG2201 | D35: LT ANA MARÍA
A36: ITCH | B36: ANALAG2202 | C36: ANALAG2202 | D36: LT ANA MARÍA
A37: ITCH | B37: CARD220-M | C37: CARD220-M | D37: MTTO_CAR 220KV
A38: ITCH | B38: CARD220-O | C38: CARD220-O | D38: OP_CAR 220KV
A39: ITCH | B39: CARD2J14PL | C39: CARD2J14PL | D39: PL CAR220
A40: ITCH | B40: CARD2J15PL | C40: CARD2J15PL | D40: PL CAR220
A41: ITCH | B41: CARD2MCOMU | C41: CARD2MCOMU | D41: MC CAR220KV
A42: ITCH | B42: CARNCA2201 | C42: CARNCA2201 | D42: LT CAR
A43: ITCH | B43: CARNCA2202 | C43: CARNCA2202 | D43: LT CAR
A44: ITCH | B44: CIERRE | C44: CIERRE | D44: CIERRE ANUAL
A45: ITCH | B45: ENCANA2201 | C45: ENCANA2201 | D45: LT ENCUENTRO
A46: ITCH | B46: ENCANA2202 | C46: ENCANA2202 | D46: LT ENCUENTRO
... A191: ITCH | B191: NPAN5K0RR1 | C191: NPAN5K0RR1 | D191: MC NPAN500
A192: ITCH | B192: NPAN5K0RR2 | C192: NPAN5K0RR2 | D192: MC NPAN500 | J192: zco:objcostos
A193: ITCH | B193: NPAN5K10CS | C193: NPAN5K10CS | D193: PC NPAN500
A194: ITCH | B194: NPAN5K10MC | C194: NPAN5K10MC | D194: MC NPAN500
A195: ITCH | B195: NPAN5K10PC | C195: NPAN5K10PC | D195: PC NPAN500
A196: ITCH | B196: NPAN5K10PL | C196: NPAN5K10PL | D196: PL NPAN500
A197: ITCH | B197: NPAN5K11ME | C197: NPAN5K11ME | D197: NPAN500
A198: ITCH | B198: NPAN5K12CS | C198: NPAN5K12CS | D198: PC NPAN500
A199: ITCH | B199: NPAN5K12MC | C199: NPAN5K12MC | D199: MC NPAN500
A200: ITCH | B200: NPAN5K12PC | C200: NPAN5K12PC | D200: PC NPAN500
A201: ITCH | B201: NPAN5K12PL | C201: NPAN5K12PL | D201: PL NPAN500
A202: ITCH | B202: NPAN5MCOMU | C202: NPAN5MCOMU | D202: NPAN500
A203: ITCH | B203: NPAN5TRAFR | C203: NPAN5TRAFR | D203: NPAN500
A204: ITCH | B204: NPAPAZ2201 | C204: NPAPAZ2201 | D204: LT NPAN
... A226: ITCH | B226: POLP5MCOMU | C226: POLP5MCOMU | D226: POLP500
A227: TRAN | B227: 10000 | C227: 10000 | D227: GERENCIA GENERAL
A228: TRAN | B228: 10001 | C228: 10001 | D228: ABASTECIMIENTO
A229: TRAN | B229: 10002 | C229: 10002 | D229: ADMINISTRACIÓN
A230: TRAN | B230: 10003 | C230: 10003 | D230: TALENTO ORGANIZ
A231: TRAN | B231: 10004 | C231: 10004 | D231: LEGAL
A232: TRAN | B232: 10005 | C232: 10005 | D232: TI
A233: TRAN | B233: 10006 | C233: 10006 | D233: NUEVOS NEGOCIOS
A234: TRAN | B234: 10007 | C234: 10007 | D234: SST
A235: TRAN | B235: 10008 | C235: 10008 | D235: ESTRATEGIA
A236: TRAN | B236: 10009 | C236: 10009 | D236: ALMACÉN
A237: TRAN | B237: 12000 | C237: 12000 | D237: INCE NUEVOS NEGOCIOS
A238: TRAN | B238: 13000 | C238: 13000 | D238: INNO PROYECTO KILA
... A259: TRAN | B259: 70000 | C259: 70000 | D259: AUDITORÍA INTERNA
A260: TRAN | B260: ANALAG2201 | C260: ANALAG2201 | D260: LT ANA MARÍA
A261: TRAN | B261: ANALAG2202 | C261: ANALAG2202 | D261: LT ANA MARÍA
A262: TRAN | B262: CARD220-M | C262: CARD220-M | D262: MTTO_CAR 220KV
A263: TRAN | B263: CARD220-O | C263: CARD220-O | D263: OP_CAR 220KV
A264: TRAN | B264: CARD2J14PL | C264: CARD2J14PL | D264: PL CAR220
A265: TRAN | B265: CARD2J15PL | C265: CARD2J15PL | D265: PL CAR220
A266: TRAN | B266: CARD2MCOMU | C266: CARD2MCOMU | D266: MC CAR220KV
A267: TRAN | B267: CARNCA2201 | C267: CARNCA2201 | D267: LT CAR
A268: TRAN | B268: CARNCA2202 | C268: CARNCA2202 | D268: LT CAR
A269: TRAN | B269: CIERRE | C269: CIERRE | D269: CIERRE ANUAL
A270: TRAN | B270: ENCANA2201 | C270: ENCANA2201 | D270: LT ENCUENTRO
A271: TRAN | B271: ENCANA2202 | C271: ENCANA2202 | D271: LT ENCUENTRO
... A451: TRAN | B451: POLP5MCOMU | C451: POLP5MCOMU | D451: POLP500
A452: ISA | B452: 10000 | C452: 10000 | D452: GERENCIA GENERAL
A453: ISA | B453: 10001 | C453: 10001 | D453: ABASTECIMIENTO
A454: ISA | B454: 10002 | C454: 10002 | D454: ADMINISTRACIÓN
A455: ISA | B455: 10003 | C455: 10003 | D455: TALENTO ORGANIZ
A456: ISA | B456: 10004 | C456: 10004 | D456: LEGAL
A457: ISA | B457: 10005 | C457: 10005 | D457: TI
A458: ISA | B458: 10006 | C458: 10006 | D458: NUEVOS NEGOCIOS
A459: ISA | B459: 10007 | C459: 10007 | D459: SST
A460: ISA | B460: 10008 | C460: 10008 | D460: ESTRATEGIA
A461: ISA | B461: 10009 | C461: 10009 | D461: ALMACÉN
A462: ISA | B462: 12000 | C462: 12000 | D462: INCE NUEVOS NEGOCIOS
A463: ISA | B463: 13000 | C463: 13000 | D463: INNO PROYECTO KILA
... A484: ISA | B484: 70000 | C484: 70000 | D484: AUDITORÍA INTERNA
A485: ISA | B485: ANALAG2201 | C485: ANALAG2201 | D485: LT ANA MARÍA
A486: ISA | B486: ANALAG2202 | C486: ANALAG2202 | D486: LT ANA MARÍA
A487: ISA | B487: CARD220-M | C487: CARD220-M | D487: MTTO_CAR 220KV
A488: ISA | B488: CARD220-O | C488: CARD220-O | D488: OP_CAR 220KV
A489: ISA | B489: CARD2J14PL | C489: CARD2J14PL | D489: PL CAR220
A490: ISA | B490: CARD2J15PL | C490: CARD2J15PL | D490: PL CAR220
A491: ISA | B491: CARD2MCOMU | C491: CARD2MCOMU | D491: MC CAR220KV
A492: ISA | B492: CARNCA2201 | C492: CARNCA2201 | D492: LT CAR
A493: ISA | B493: CARNCA2202 | C493: CARNCA2202 | D493: LT CAR
A494: ISA | B494: CIERRE | C494: CIERRE | D494: CIERRE ANUAL
A495: ISA | B495: ENCANA2201 | C495: ENCANA2201 | D495: LT ENCUENTRO
A496: ISA | B496: ENCANA2202 | C496: ENCANA2202 | D496: LT ENCUENTRO
... A676: ISA | B676: POLP5MCOMU | C676: POLP5MCOMU | D676: POLP500
A677: CABA | B677: 10000 | C677: 10000 | D677: GERENCIA GENERAL
A678: CABA | B678: 10001 | C678: 10001 | D678: ABASTECIMIENTO
A679: CABA | B679: 10002 | C679: 10002 | D679: ADMINISTRACIÓN
A680: CABA | B680: 10003 | C680: 10003 | D680: TALENTO ORGANIZ
A681: CABA | B681: 10004 | C681: 10004 | D681: LEGAL
A682: CABA | B682: 10005 | C682: 10005 | D682: TI
A683: CABA | B683: 10006 | C683: 10006 | D683: NUEVOS NEGOCIOS
...

Sheet Emplazamiento
A1: Sociedad | B1: Emplazamiento | C1: Descripción
A2: ITCH | B2: 1101 | C2: Iquique
A3: ITCH | B3: 1107 | C3: Alto Hospicio
A4: ITCH | B4: 1401 | C4: Pozo Almonte
A5: ITCH | B5: 1402 | C5: Camiña
A6: ITCH | B6: 1403 | C6: Colchane
A7: ITCH | B7: 1404 | C7: Huara
A8: ITCH | B8: 1405 | C8: Pica
A9: ITCH | B9: 2101 | C9: Antofagasta
A10: ITCH | B10: 2102 | C10: Mejillones
A11: ITCH | B11: 2103 | C11: Sierra Gorda
A12: ITCH | B12: 2104 | C12: Taltal
A13: ITCH | B13: 2201 | C13: Calama
... A1381: CABA | B1381: 15202 | C1381: General Lagos

Sheet _ListasClase
A1: Descripción Clase (filtrada) | C1: Criterio 1 | E1: Criterio 2 | G1: Criterio 3 | I1: Criterio 4 | K1: Criterio 5 | M1: Emplazamiento | O1: Centro de Costo | Q1: Países | S1: Respuesta SI/NO
A2: {=IFERROR(_xlfn._xlws.FILTER(Clase!$C$2:$C$292, Clase!$A$2:$A$292=Formato!$C$14, ""), "")} -> Terrenos Rurales | C2: {=IFERROR(_xlfn._xlws.FILTER('Criterio '!$B$2:$B$108,'Criterio '!$A$2:$A$108=Formato!$C$14,""),"")} -> 0 | E2: {=IFERROR(_xlfn._xlws.FILTER('Criterio '!$D$2:$D$108,'Criterio '!$A$2:$A$108=Formato!$C$14,""),"")} -> 0 | G2: {=IFERROR(_xlfn._xlws.FILTER('Criterio '!$F$2:$F$108,'Criterio '!$A$2:$A$108=Formato!$C$14,""),"")} -> IC01 | I2: {=IFERROR(_xlfn._xlws.FILTER('Criterio '!$H$2:$H$108,'Criterio '!$A$2:$A$108=Formato!$C$14,""),"")} -> 0 | K2: {=IFERROR(_xlfn._xlws.FILTER('Criterio '!$J$2:$J$108,'Criterio '!$A$2:$A$108=Formato!$C$14,""),"")} -> ICA10000 | M2: {=IFERROR(_xlfn._xlws.FILTER(Emplazamiento!$B$2:$B$1381,Emplazamiento!$A$2:$A$1381=Formato!$C$14,""),"")} -> 1101 | O2: {=IFERROR(_xlfn._xlws.FILTER(Ceco!$B$2:$B$901,Ceco!$A$2:$A$901=Formato!$C$14,""),"")} -> 10000 | Q2: {=IFERROR(_xlfn.UNIQUE(_xlfn._xlws.FILTER(Sociedades!$B$2:$B$10,Sociedades!$B$2:$B$10<>"")),"")} -> Colombia | S2: SI
A3: Terrenos Urbanos | C3: 0 | E3: 0 | G3: IC02 | I3: 0 | K3: ICO10000 | M3: 1107 | O3: 10001 | Q3: Chile | S3: NO
A4: Terrenos Urbanos 2 | C4: 0 | E4: 0 | G4: IC03 | I4: 0 | K4: ICO20000 | M4: 1401 | O4: 10002 | Q4: Perú
A5: Terrenos no explotados - Prop.Inversión | C5: 0 | E5: 0 | G5: IC04 | I5: 0 | K5: P001L001 | M5: 1402 | O5: 10003
A6: Terrenos Urbanos | C6: 0 | E6: 0 | G6: IC05 | I6: 0 | K6: P001L002 | M6: 1403 | O6: 10004
A7: Terrenos Rurales | C7: 0 | E7: 0 | G7: IC06 | I7: 0 | K7: P001L003 | M7: 1404 | O7: 10005
A8: Terrenos no explotados - Prop.Inversión | C8: 0 | E8: 0 | G8: IC07 | I8: 0 | K8: P001S001 | M8: 1405 | O8: 10006
A9: Terrenos Urbanos Leasing | C9: 0 | E9: 0 | G9: IC08 | I9: 0 | K9: P001S002 | M9: 2101 | O9: 10007
A10: Redes, Lineas y Cables (Costos Directos) | C10: 0 | E10: 0 | G10: IC09 | I10: 0 | K10: P001S003 | M10: 2102 | O10: 10008
A11: Redes, Lineas y Cables (Gastos de Adm.Cap. Direc) | C11: 0 | E11: 0 | G11: IC11 | I11: 0 | K11: P001S004 | M11: 2103 | O11: 10009
A12: Redes, Lineas y Cables (Gastos de Adm.Cap. Indirec | C12: 0 | E12: 0 | G12: IC12 | I12: 0 | K12: P001S005 | M12: 2104 | O12: 12000
A13: Redes, Lineas y Cables (Ajustes por Inflacion) | C13: 0 | E13: 0 | G13: ICA1 | I13: 0 | K13: P001S006 | M13: 2201 | O13: 13000
A14: Redes, Lineas y Cables (Gastos Financieros) | C14: 0 | E14: 0 | G14: ICO1 | I14: 0 | K14: P001S007 | M14: 2202 | O14: 13000
A15: Redes, Lineas y Cables (Comisiones Financieras) | C15: 0 | E15: 0 | G15: ICO2 | I15: 0 | K15: P002L004 | M15: 2203 | O15: 20000
A16: Plantas y Ductos (Costos Directos) | C16: 0 | E16: 0 | G16: 0 | I16: 0 | K16: P002S008 | M16: 2301 | O16: 30000
A17: Plantas y Ductos (Gastos de Adm.Cap. Direc) | C17: 0 | E17: 0 | G17: 0 | I17: 0 | K17: P002S009 | M17: 2302 | O17: 30000
A18: Plantas y Ductos (Gastos de Adm.Cap. Indirec) | C18: 0 | E18: 0 | G18: 0 | I18: 0 | K18: P003L004 | M18: 3101 | O18: 30001
A19: Edificaciones (Costos directos) | C19: 0 | E19: 0 | G19: 0 | I19: 0 | K19: P003S008 | M19: 3102 | O19: 30002
A20: Plantas y Ductos (Ajustes por Inflacion) | C20: 0 | E20: 0 | G20: 0 | I20: 0 | K20: P003S009 | M20: 3103 | O20: 30003
A21: Plantas y Ductos (Gastos Financieros) | C21: 0 | E21: 0 | G21: 0 | I21: 0 | K21: P004S001 | M21: 3201 | O21: 40000
A22: Plantas y Ductos (Comisiones Financieras) | C22: 0 | E22: 0 | G22: 0 | I22: 0 | K22: P004S003 | M22: 3202 | O22: 40000
A23: Plantas y Ductos (Costos Directos) Saldo inicial | C23: 0 | E23: 0 | G23: 0 | I23: 0 | K23: P004S005 | M23: 3301 | O23: 40001
A24: Eq de Comun y Computo (Costos Directo) | C24: 0 | E24: 0 | G24: 0 | I24: 0 | K24: P005S001 | M24: 3302 | O24: 40002
A25: Eq de Comun y Computo (Gastos Financieros) | C25: 0 | E25: 0 | G25: 0 | I25: 0 | K25: P007S011 | M25: 3303 | O25: 40003
A26: Eq de Comun y Computo (Gastos de Adm.Cap. Direc) | C26: 0 | E26: 0 | G26: 0 | I26: 0 | K26: P008S012 | M26: 3304 | O26: 40004
A27: Eq de Comun y Computo (Gastos de Adm.Cap. Ind) | C27: 0 | E27: 0 | G27: 0 | I27: 0 | K27: P009S013 | M27: 4101 | O27: 40005
... A30: Redes, Lineas y Cables (Costos Directos) DP | C30: 0 | E30: 0 | G30: 0 | I30: 0 | K30: ICO20000 | M30: 4104 | O30: 60000
A31: Redes, Lineas y Cables (Ajustes por Inflacion)DP | M31: 4105 | O31: 60001
A32: Redes, Lineas y Cables(Gastos de Adm.Cap. Direc)DP | M32: 4106 | O32: 60002
A33: Redes,LineasyCables(Gastos de Adm.Cap. Indirec)DP | M33: 4201 | O33: 60003
A34: Redes, Lineas y Cables (Dif. en Cam Obli Finan) DP | M34: 4202 | O34: 70000
A35: Redes, Lineas y Cables (Gastos Financieros) DP | M35: 4203 | O35: ANALAG2201
A36: Plantas y Ductos (Dif. en Cambio Obli Finan) DP | M36: 4204 | O36: ANALAG2202
A37: Plantas y Ductos (Gastos Financieros) DP | M37: 4301 | O37: CARD220-M
A38: Plantas y Ductos (Gastos de Adm.Cap. Direc) DP | M38: 4302 | O38: CARD220-O
A39: Plantas y Ductos (Gastos de Adm.Cap. Indirec) DP | M39: 4303 | O39: CARD2J14PL
A40: Plantas y Ductos (Ajustes por Inflacion) DP | M40: 4304 | O40: CARD2J15PL
A41: Eq de Comun y Computo (Costos Directo) Ordenes de | M41: 4305 | O41: CARD2MCOMU
A42: Eq de Comun y Computo (Gastos de Adm.Cap. Direc) O | M42: 5101 | O42: CARNCA2201
A43: Eq de Comun y Computo (Gastos de Adm.Cap. Ind) Or | M43: 5102 | O43: CARNCA2202
A44: Eq de Comun y Computo (Ajuste por Inflacion) Orde | M44: 5103 | O44: CIERRE
A45: Eq de Comun y Computo (Dif. en Cam Obli Finan) Ord | M45: 5104 | O45: ENCANA2201
A46: Eq de Comun y Computo (Gastos Financieros) Ordenes | M46: 5105 | O46: ENCANA2202
... A181: Arrend Financ Equi Instal Subest_Biens | M181: 8406 | O181: NPAN5K06PC
M182: 8407 | O182: NPAN5K07CS
M183: 8408 | O183: NPAN5K07MC
M184: 8409 | O184: NPAN5K07PC
M185: 8410 | O185: NPAN5K07PL
M186: 8411 | O186: NPAN5K08ME
M187: 8412 | O187: NPAN5K09CS
M188: 8413 | O188: NPAN5K09MC
M189: 8414 | O189: NPAN5K09PC
M190: 8415 | O190: NPAN5K09PL
M191: 8416 | O191: NPAN5K0RR1
M192: 8417 | O192: NPAN5K0RR2
M193: 8418 | O193: NPAN5K10CS
... M226: 9209 | O226: POLP5MCOMU
M227: 9210
M228: 9211
M229: 10101
M230: 10102
M231: 10103
M232: 10104
M233: 10105
M234: 10106
M235: 10107
M236: 10108
M237: 10109
M238: 10201
... M346: 15202

Sheet _Requeridos
A1: CONFIGURACIÓN DE CAMPOS REQUERIDOS POR SOCIEDAD | Z1: [{"reqCol":1,"fmtCol":"C","name":"Orden de Inversión"},{"reqCol":2,"fmtCol":"D","name":"Elemento PEP"},{"reqCol":3,"fmtCol":"E","name":"Pedido"},{"reqCol":4,"fmtCol":"F","name":"Descripción Activo SAP"},{"reqCol":5,"fmtCol":"G","name":"Clase"},{"reqCol":6,"fmtCol":"H","name":"Cantidad"},{"reqCol":7,"fmtCol":"I","name":"Nombre principal AF"},{"reqCol":8,"fmtCol":"L","name":"Fabricante"},{"reqCol":9,"fmtCol":"M","name":"Nit Proveedor"},{"reqCol":10,"fmtCol":"N","name":"Serie"},{"reqCol":11,"fmtCol":"P","name":"Criterio de Clasificación 1"},{"reqCol":12,"fmtCol":"Q","name":"Criterio de Clasificación 2"},{"reqCol":13,"fmtCol":"R","name":"Criterio de Clasificación 3"},{"reqCol":14,"fmtCol":"S","name":"Criterio de Clasificación 4"},{"reqCol":15,"fmtCol":"T","name":"Criterio de Clasificación 5"},{"reqCol":16,"fmtCol":"U","name":"Ubicación técnica"},{"reqCol":17,"fmtCol":"X","name":"Centro"},{"reqCol":18,"fmtCol":"Y","name":"Código País"},{"reqCol":19,"fmtCol":"Z","name":"Emplazamiento"},{"reqCol":20,"fmtCol":"AB","name":"Centro de Costo"},{"reqCol":21,"fmtCol":"AC","name":"Número de personal"},{"reqCol":22,"fmtCol":"AH","name":"Valor Unitario"}]
A3: ℹ️ INSTRUCCIONES:
A4: • En la tabla siguiente, escriba SI en la celda correspondiente a Sociedad + Campo para marcarlo como REQUERIDO.
A5: • Deje en blanco o escriba NO si el campo NO es requerido para esa sociedad.
A6: • Puede agregar nuevas sociedades en nuevas filas siguiendo el mismo formato.
A7: • Los cambios aquí se reflejan automáticamente en la validación del Formato.
A8: Col. Formato → | B8: C | C8: D | D8: E | E8: F | F8: G | G8: H | H8: I | I8: L | J8: M | K8: N | L8: P | M8: Q | N8: R | O8: S | P8: T | Q8: U | R8: X | S8: Y | T8: Z | U8: AB | V8: AC | W8: AH
A9: Sociedad | B9: Orden de Inversión | C9: Elemento PEP | D9: Pedido | E9: Descripción Activo SAP | F9: Clase | G9: Cantidad | H9: Nombre principal AF | I9: Fabricante | J9: Nit Proveedor | K9: Serie | L9: Criterio Clas. 1 | M9: Criterio Clas. 2 | N9: Criterio Clas. 3 | O9: Criterio Clas. 4 | P9: Criterio Clas. 5 | Q9: Ubicación técnica | R9: Centro | S9: Código País | T9: Emplazamiento | U9: Centro de Costo | V9: Número de personal | W9: Valor Unitario
A10: TRAN | B10: SI | C10: SI | E10: SI | F10: SI | G10: SI | H10: SI | N10: SI | P10: SI | R10: SI | T10: SI | U10: SI | W10: SI
A11: ISA | E11: SI | F11: SI | L11: NO | T11: SI
A12: ITCH | B12: SI | C12: SI | E12: SI | F12: SI | G12: SI | H12: SI | N12: SI | P12: SI | R12: SI | T12: SI | U12: SI | W12: SI
A13: CABA | E13: SI | F13: SI | G13: SI | H13: SI | L13: SI | M13: SI | N13: SI | O13: SI | S13: SI | T13: SI | U13: SI | W13: SI
A16: CONFIGURACIÓN PREGUNTAS CHECKLIST POR PAÍS
A17: ℹ️ Escriba SI para mostrar la pregunta en ese país. Deje vacío o NO para ocultarla.
A18: ℹ️ Para agregar un nuevo país: agregue una nueva fila con el nombre del país y sus SI/NO.
A20: País → | B20: P1 | C20: P2 | D20: P3 | E20: P4 | F20: P5 | G20: P6 | H20: P7 | I20: P8 | J20: P9 | K20: P10 | L20: P11
A21: Colombia | B21: SI | C21: SI | D21: SI | E21: SI | F21: SI | G21: SI
A22: Perú | H22: SI | I22: SI | J22: SI | K22: SI | L22: SI
A23: Chile | B23: SI | C23: SI | D23: SI | E23: SI | G23: SI

Sheet Check list
B8: ✅ Checklist de Validación
B11: ✅ Paso 1: Seleccione la PAIS a la cual se realizará la creación de activos.
B12: ✅ Paso 2: Seleccione una respuesta del siguiente listado (SI/NO)
B14: FILIAL | C14: ISA
B17: Preguntas | C17: Respuesta
B18: 1. ¿El activo es un recurso tangible controlado por la compañía? | C18: SI
B19: 2. ¿Se espera que el activo sea utilizado en el giro normal del negocio por más de un año? | C19: SI
B20: 3. ¿Es probable que el activo genere beneficios económicos o apoye funciones administrativas? | C20: SI
B21: 4. ¿Su valor puede ser medido de forma confiable y razonable? | C21: SI
B22: 5. ¿El valor del activo supera 2.5 Salarios Mínimos Mensuales Legales Vigentes (SMMLV)? | C22: SI
B23: 6. ¿Es de interés para la organización, de tal forma que esté dispuesta a realizarle seguimiento y control como propiedad, planta y equipo? | C23: SI
B25: ¿PUEDE SER CREADO COMO ACTIVO FIJO? | C25: =IF(C14="","Seleccione un país válido",IF(COUNTIFS(B18:B23,"<>""",C18:C23,"NO")>0,"NO CUMPLE","CUMPLE")) -> CUMPLE
B27: EXCLUSIVO PARA FILIALES DE PERÚ
B28: 7. ¿El activo supera el valor de 1/4 de UIT (Unidad Impositiva Tributaria)? | C28: SI
B29: 8. ¿El equipo va a ser reemplazado en alguna concesión? | C29: SI
B30: 9. ¿Pertenece a un proyecto? | C30: SI
B31: 10. ¿Se compra a través de una orden estadística según tipo de activo (diversos, inmuebles)? | C31: SI
B32: 11. ¿El activo no está sincronizado AA-PM por la fecha de montaje y esta se reporta al Ministerio/Osinerming? | C32: SI
C34: =IF(C14="","Seleccione un país válido",IF(COUNTIFS(B28:B32,"<>""",C28:C32,"NO")>0,"NO CUMPLE","CUMPLE")) -> CUMPLE
B37: WARNING

Sheet Formato
B11: FORMATO CREACIÓN Y CAPITALIZACIÓN DE ACTIVOS FIJOS
B14: SOCIEDAD: | C14: ISA
B15: FECHA:
B16: ÁREA:
B17: RESPONSABLE DEL ACTIVO FIJO:
B18: LIDER DE ÁREA:
B19: SOLICITUD:
AG20: Aplica solo para Liquidación de Proyectos
B21: Ítem | C21: Orden de Inversión | D21: Elemento PEP | E21: Pedido | F21: Descipción Activo SAP | G21: Clase Clase | H21: Cantidad | I21: Nombre principal del activo fijo | J21: Nombre del activo fijo (información adicional) | K21: Nombre del activo fijo (información adicional) | L21: Fabricante | M21: Nit Proveedor | N21: Serie | O21: Denominación Tipo | P21: Criterio de Clasificación 1 | Q21: Criterio de Clasificación 2 | R21: Criterio de Clasificación 3 | S21: Criterio de Clasificación 4 | T21: Criterio de Clasificación 5 | U21: Ubicación técnica | V21: Activo eléctrico/No Eléctrico | W21: Contrato Conexión/UPME | X21: Centro | Y21: Código País | Z21: Emplazamiento | AA21: Material (Número de Inventario) | AB21: Centro de Costo | AC21: Número de personal | AD21: Centro de Costo Responsable | AE21: Subestación | AF21: Vida Útil Estimada | AG21: Activo Fijo | AH21: Valor Unitario | AI21: Porcentaje | AJ21: Estado de registro
B22: 1 | D22: RI-POAS1-1.2.02 | F22: Equipos de Subestación Nueva Estructura 15 Años | G22: =IFERROR(_xlfn.XLOOKUP(F22,Clase!$C$2:$C$292,Clase!$B$2:$B$292,""),"") -> A451217 | H22: 1 | I22: Controlador campo - Prueba 100 | J22: Controlador campo - Prueba 3 | K22: Controlador campo - Prueba 3 | L22: SIEMENS | N22: BM2501019994 | R22: IC03 | T22: P003S009 | U22: SCAR230M03ME-SASCC | W22: 4510014034 | X22: Tran | Z22: 5603 | AB22: 10004 | AD22: =IFERROR(_xlfn.XLOOKUP(AB22,Ceco!$B$2:$B$901,Ceco!$C$2:$C$901,""),"") -> 10004 | AJ22: =IF(COUNTA(C22,D22,E22,F22,H22,I22,L22,M22,N22,P22,Q22,R22,S22,T22,U22,X22,Y22,Z22,AB22,AC22,AH22)=0,"",IF(LEN(_xlfn.TEXTJOIN(", ",TRUE,IF(AND(_xlfn.XLOOKUP($C$14,_Requeridos!$A$10:$A$20,_Requeridos!$B$10:$B$20,"")="SI",C22=""),"Orden de Inversión",""),IF(AND(_xlfn.XLOOKUP($C$14,_Requeridos!$A$10:$A$20,_Requeridos!$C$10:$C$20,"")="SI",D22=""),"Elemento PEP",""),IF(AND(_xlfn.XLOOKUP($C$14,_Requeridos!$A$10:$A$20,_Requeridos!$D$10:$D$20,"")="SI",E22=""),"Pedido",""),IF(AND(_xlfn.XLOOKUP($C$14,_Requeridos!$A$10:$A$20,_Requeridos!$E$10:$E$20,"")="SI",F22=""),"Descripción Activo SAP",""),IF(AND(_xlfn.XLOOKUP($C$14,_Requeridos!$A$10:$A$20,_Requeridos!$F$10:$F$20,"")="SI",G22=""),"Clase",""),IF(AND(_xlfn.XLOOKUP($C$14,_Requeridos!$A$10:$A$20,_Requeridos!$G$10:$G$20,"")="SI",H22=""),"Cantidad",""),IF(AND(_xlfn.XLOOKUP($C$14,_Requeridos!$A$10:$A$20,_Requeridos!$H$10:$H$20,"")="SI",I22=""),"Nombre principal AF",""),IF(AND(_xlfn.XLOOKUP($C$14,_Requeridos!$A$10:$A$20,_Requeridos!$I$10:$I$20,"")="SI",L22=""),"Fabricante",""),IF(AND(_xlfn.XLOOKUP($C$14,_Requeridos!$A$10:$A$20,_Requeridos!$J$10:$J$20,"")="SI",M22=""),"Nit Proveedor",""),IF(AND(_xlfn.XLOOKUP($C$14,_Requeridos!$A$10:$A$20,_Requeridos!$K$10:$K$20,"")="SI",N22=""),"Serie",""),IF(AND(_xlfn.XLOOKUP($C$14,_Requeridos!$A$10:$A$20,_Requeridos!$L$10:$L$20,"")="SI",P22=""),"Criterio Clas. 1",""),IF(AND(_xlfn.XLOOKUP($C$14,_Requeridos!$A$10:$A$20,_Requeridos!$M$10:$M$20,"")="SI",Q22=""),"Criterio Clas. 2",""),IF(AND(_xlfn.XLOOKUP($C$14,_Requeridos!$A$10:$A$20,_Requeridos!$N$10:$N$20,"")="SI",R22=""),"Criterio Clas. 3",""),IF(AND(_xlfn.XLOOKUP($C$14,_Requeridos!$A$10:$A$20,_Requeridos!$O$10:$O$20,"")="SI",S22=""),"Criterio Clas. 4",""),IF(AND(_xlfn.XLOOKUP($C$14,_Requeridos!$A$10:$A$20,_Requeridos!$P$10:$P$20,"")="SI",T22=""),"Criterio Clas. 5",""),IF(AND(_xlfn.XLOOKUP($C$14,_Requeridos!$A$10:$A$20,_Requeridos!$Q$10:$Q$20,"")="SI",U22=""),"Ubicación técnica",""),IF(AND(_xlfn.XLOOKUP($C$14,_Requeridos!$A$10:$A$20,_Requeridos!$R$10:$R$20,"")="SI",X22=""),"Centro",""),IF(AND(_xlfn.XLOOKUP($C$14,_Requeridos!$A$10:$A$20,_Requeridos!$S$10:$S$20,"")="SI",Y22=""),"Código País",""),IF(AND(_xlfn.XLOOKUP($C$14,_Requeridos!$A$10:$A$20,_Requeridos!$T$10:$T$20,"")="SI",Z22=""),"Emplazamiento",""),IF(AND(_xlfn.XLOOKUP($C$14,_Requeridos!$A$10:$A$20,_Requeridos!$U$10:$U$20,"")="SI",AB22=""),"Centro de Costo",""),IF(AND(_xlfn.XLOOKUP($C$14,_Requeridos!$A$10:$A$20,_Requeridos!$V$10:$V$20,"")="SI",AC22=""),"Número de personal",""),IF(AND(_xlfn.XLOOKUP($C$14,_Requeridos!$A$10:$A$20,_Requeridos!$W$10:$W$20,"")="SI",AH22=""),"Valor Unitario","")))>0,"⚠️ Faltan: "&_xlfn.TEXTJOIN(", ",TRUE,IF(AND(_xlfn.XLOOKUP($C$14,_Requeridos!$A$10:$A$20,_Requeridos!$B$10:$B$20,"")="SI",C22=""),"Orden de Inversión",""),IF(AND(_xlfn.XLOOKUP($C$14,_Requeridos!$A$10:$A$20,_Requeridos!$C$10:$C$20,"")="SI",D22=""),"Elemento PEP",""),IF(AND(_xlfn.XLOOKUP($C$14,_Requeridos!$A$10:$A$20,_Requeridos!$D$10:$D$20,"")="SI",E22=""),"Pedido",""),IF(AND(_xlfn.XLOOKUP($C$14,_Requeridos!$A$10:$A$20,_Requeridos!$E$10:$E$20,"")="SI",F22=""),"Descripción Activo SAP",""),IF(AND(_xlfn.XLOOKUP($C$14,_Requeridos!$A$10:$A$20,_Requeridos!$F$10:$F$20,"")="SI",G22=""),"Clase",""),IF(AND(_xlfn.XLOOKUP($C$14,_Requeridos!$A$10:$A$20,_Requeridos!$G$10:$G$20,"")="SI",H22=""),"Cantidad",""),IF(AND(_xlfn.XLOOKUP($C$14,_Requeridos!$A$10:$A$20,_Requeridos!$H$10:$H$20,"")="SI",I22=""),"Nombre principal AF",""),IF(AND(_xlfn.XLOOKUP($C$14,_Requeridos!$A$10:$A$20,_Requeridos!$I$10:$I$20,"")="SI",L22=""),"Fabricante",""),IF(AND(_xlfn.XLOOKUP($C$14,_Requeridos!$A$10:$A$20,_Requeridos!$J$10:$J$20,"")="SI",M22=""),"Nit Proveedor",""),IF(AND(_xlfn.XLOOKUP($C$14,_Requeridos!$A$10:$A$20,_Requeridos!$K$10:$K$20,"")="SI",N22=""),"Serie",""),IF(AND(_xlfn.XLOOKUP($C$14,_Requeridos!$A$10:$A$20,_Requeridos!$L$10:$L$20,"")="SI",P22=""),"Criterio Clas. 1",""),IF(AND(_xlfn.XLOOKUP($C$14,_Requeridos!$A$10:$A$20,_Requeridos!$M$10:$M$20,"")="SI",Q22=""),"Criterio Clas. 2",""),IF(AND(_xlfn.XLOOKUP($C$14,_Requeridos!$A$10:$A$20,_Requeridos!$N$10:$N$20,"")="SI",R22=""),"Criterio Clas. 3",""),IF(AND(_xlfn.XLOOKUP($C$14,_Requeridos!$A$10:$A$20,_Requeridos!$O$10:$O$20,"")="SI",S22=""),"Criterio Clas. 4",""),IF(AND(_xlfn.XLOOKUP($C$14,_Requeridos!$A$10:$A$20,_Requeridos!$P$10:$P$20,"")="SI",T22=""),"Criterio Clas. 5",""),IF(AND(_xlfn.XLOOKUP($C$14,_Requeridos!$A$10:$A$20,_Requeridos!$Q$10:$Q$20,"")="SI",U22=""),"Ubicación técnica",""),IF(AND(_xlfn.XLOOKUP($C$14,_Requeridos!$A$10:$A$20,_Requeridos!$R$10:$R$20,"")="SI",X22=""),"Centro",""),IF(AND(_xlfn.XLOOKUP($C$14,_Requeridos!$A$10:$A$20,_Requeridos!$S$10:$S$20,"")="SI",Y22=""),"Código País",""),IF(AND(_xlfn.XLOOKUP($C$14,_Requeridos!$A$10:$A$20,_Requeridos!$T$10:$T$20,"")="SI",Z22=""),"Emplazamiento",""),IF(AND(_xlfn.XLOOKUP($C$14,_Requeridos!$A$10:$A$20,_Requeridos!$U$10:$U$20,"")="SI",AB22=""),"Centro de Costo",""),IF(AND(_xlfn.XLOOKUP($C$14,_Requeridos!$A$10:$A$20,_Requeridos!$V$10:$V$20,"")="SI",AC22=""),"Número de personal",""),IF(AND(_xlfn.XLOOKUP($C$14,_Requeridos!$A$10:$A$20,_Requeridos!$W$10:$W$20,"")="SI",AH22=""),"Valor Unitario","")),"✅ Completo")) -> ✅ Completo
B23: 2 | G23: =IFERROR(_xlfn.XLOOKUP(F23,Clase!$C$2:$C$292,Clase!$B$2:$B$292,""),"") | AD23: =IFERROR(_xlfn.XLOOKUP(AB23,Ceco!$B$2:$B$901,Ceco!$C$2:$C$901,""),"") | AJ23: =IF(COUNTA(C23,D23,E23,F23,H23,I23,L23,M23,N23,P23,Q23,R23,S23,T23,U23,X23,Y23,Z23,AB23,AC23,AH23)=0,"",IF(LEN(_xlfn.TEXTJOIN(", ",TRUE,IF(AND(_xlfn.XLOOKUP($C$14,_Requeridos!$A$10:$A$20,_Requeridos!$B$10:$B$20,"")="SI",C23=""),"Orden de Inversión",""),IF(AND(_xlfn.XLOOKUP($C$14,_Requeridos!$A$10:$A$20,_Requeridos!$C$10:$C$20,"")="SI",D23=""),"Elemento PEP",""),IF(AND(_xlfn.XLOOKUP($C$14,_Requeridos!$A$10:$A$20,_Requeridos!$D$10:$D$20,"")="SI",E23=""),"Pedido",""),IF(AND(_xlfn.XLOOKUP($C$14,_Requeridos!$A$10:$A$20,_Requeridos!$E$10:$E$20,"")="SI",F23=""),"Descripción Activo SAP",""),IF(AND(_xlfn.XLOOKUP($C$14,_Requeridos!$A$10:$A$20,_Requeridos!$F$10:$F$20,"")="SI",G23=""),"Clase",""),IF(AND(_xlfn.XLOOKUP($C$14,_Requeridos!$A$10:$A$20,_Requeridos!$G$10:$G$20,"")="SI",H23=""),"Cantidad",""),IF(AND(_xlfn.XLOOKUP($C$14,_Requeridos!$A$10:$A$20,_Requeridos!$H$10:$H$20,"")="SI",I23=""),"Nombre principal AF",""),IF(AND(_xlfn.XLOOKUP($C$14,_Requeridos!$A$10:$A$20,_Requeridos!$I$10:$I$20,"")="SI",L23=""),"Fabricante",""),IF(AND(_xlfn.XLOOKUP($C$14,_Requeridos!$A$10:$A$20,_Requeridos!$J$10:$J$20,"")="SI",M23=""),"Nit Proveedor",""),IF(AND(_xlfn.XLOOKUP($C$14,_Requeridos!$A$10:$A$20,_Requeridos!$K$10:$K$20,"")="SI",N23=""),"Serie",""),IF(AND(_xlfn.XLOOKUP($C$14,_Requeridos!$A$10:$A$20,_Requeridos!$L$10:$L$20,"")="SI",P23=""),"Criterio Clas. 1",""),IF(AND(_xlfn.XLOOKUP($C$14,_Requeridos!$A$10:$A$20,_Requeridos!$M$10:$M$20,"")="SI",Q23=""),"Criterio Clas. 2",""),IF(AND(_xlfn.XLOOKUP($C$14,_Requeridos!$A$10:$A$20,_Requeridos!$N$10:$N$20,"")="SI",R23=""),"Criterio Clas. 3",""),IF(AND(_xlfn.XLOOKUP($C$14,_Requeridos!$A$10:$A$20,_Requeridos!$O$10:$O$20,"")="SI",S23=""),"Criterio Clas. 4",""),IF(AND(_xlfn.XLOOKUP($C$14,_Requeridos!$A$10:$A$20,_Requeridos!$P$10:$P$20,"")="SI",T23=""),"Criterio Clas. 5",""),IF(AND(_xlfn.XLOOKUP($C$14,_Requeridos!$A$10:$A$20,_Requeridos!$Q$10:$Q$20,"")="SI",U23=""),"Ubicación técnica",""),IF(AND(_xlfn.XLOOKUP($C$14,_Requeridos!$A$10:$A$20,_Requeridos!$R$10:$R$20,"")="SI",X23=""),"Centro",""),IF(AND(_xlfn.XLOOKUP($C$14,_Requeridos!$A$10:$A$20,_Requeridos!$S$10:$S$20,"")="SI",Y23=""),"Código País",""),IF(AND(_xlfn.XLOOKUP($C$14,_Requeridos!$A$10:$A$20,_Requeridos!$T$10:$T$20,"")="SI",Z23=""),"Emplazamiento",""),IF(AND(_xlfn.XLOOKUP($C$14,_Requeridos!$A$10:$A$20,_Requeridos!$U$10:$U$20,"")="SI",AB23=""),"Centro de Costo",""),IF(AND(_xlfn.XLOOKUP($C$14,_Requeridos!$A$10:$A$20,_Requeridos!$V$10:$V$20,"")="SI",AC23=""),"Número de personal",""),IF(AND(_xlfn.XLOOKUP($C$14,_Requeridos!$A$10:$A$20,_Requeridos!$W$10:$W$20,"")="SI",AH23=""),"Valor Unitario","")))>0,"⚠️ Faltan: "&_xlfn.TEXTJOIN(", ",TRUE,IF(AND(_xlfn.XLOOKUP($C$14,_Requeridos!$A$10:$A$20,_Requeridos!$B$10:$B$20,"")="SI",C23=""),"Orden de Inversión",""),IF(AND(_xlfn.XLOOKUP($C$14,_Requeridos!$A$10:$A$20,_Requeridos!$C$10:$C$20,"")="SI",D23=""),"Elemento PEP",""),IF(AND(_xlfn.XLOOKUP($C$14,_Requeridos!$A$10:$A$20,_Requeridos!$D$10:$D$20,"")="SI",E23=""),"Pedido",""),IF(AND(_xlfn.XLOOKUP($C$14,_Requeridos!$A$10:$A$20,_Requeridos!$E$10:$E$20,"")="SI",F23=""),"Descripción Activo SAP",""),IF(AND(_xlfn.XLOOKUP($C$14,_Requeridos!$A$10:$A$20,_Requeridos!$F$10:$F$20,"")="SI",G23=""),"Clase",""),IF(AND(_xlfn.XLOOKUP($C$14,_Requeridos!$A$10:$A$20,_Requeridos!$G$10:$G$20,"")="SI",H23=""),"Cantidad",""),IF(AND(_xlfn.XLOOKUP($C$14,_Requeridos!$A$10:$A$20,_Requeridos!$H$10:$H$20,"")="SI",I23=""),"Nombre principal AF",""),IF(AND(_xlfn.XLOOKUP($C$14,_Requeridos!$A$10:$A$20,_Requeridos!$I$10:$I$20,"")="SI",L23=""),"Fabricante",""),IF(AND(_xlfn.XLOOKUP($C$14,_Requeridos!$A$10:$A$20,_Requeridos!$J$10:$J$20,"")="SI",M23=""),"Nit Proveedor",""),IF(AND(_xlfn.XLOOKUP($C$14,_Requeridos!$A$10:$A$20,_Requeridos!$K$10:$K$20,"")="SI",N23=""),"Serie",""),IF(AND(_xlfn.XLOOKUP($C$14,_Requeridos!$A$10:$A$20,_Requeridos!$L$10:$L$20,"")="SI",P23=""),"Criterio Clas. 1",""),IF(AND(_xlfn.XLOOKUP($C$14,_Requeridos!$A$10:$A$20,_Requeridos!$M$10:$M$20,"")="SI",Q23=""),"Criterio Clas. 2",""),IF(AND(_xlfn.XLOOKUP($C$14,_Requeridos!$A$10:$A$20,_Requeridos!$N$10:$N$20,"")="SI",R23=""),"Criterio Clas. 3",""),IF(AND(_xlfn.XLOOKUP($C$14,_Requeridos!$A$10:$A$20,_Requeridos!$O$10:$O$20,"")="SI",S23=""),"Criterio Clas. 4",""),IF(AND(_xlfn.XLOOKUP($C$14,_Requeridos!$A$10:$A$20,_Requeridos!$P$10:$P$20,"")="SI",T23=""),"Criterio Clas. 5",""),IF(AND(_xlfn.XLOOKUP($C$14,_Requeridos!$A$10:$A$20,_Requeridos!$Q$10:$Q$20,"")="SI",U23=""),"Ubicación técnica",""),IF(AND(_xlfn.XLOOKUP($C$14,_Requeridos!$A$10:$A$20,_Requeridos!$R$10:$R$20,"")="SI",X23=""),"Centro",""),IF(AND(_xlfn.XLOOKUP($C$14,_Requeridos!$A$10:$A$20,_Requeridos!$S$10:$S$20,"")="SI",Y23=""),"Código País",""),IF(AND(_xlfn.XLOOKUP($C$14,_Requeridos!$A$10:$A$20,_Requeridos!$T$10:$T$20,"")="SI",Z23=""),"Emplazamiento",""),IF(AND(_xlfn.XLOOKUP($C$14,_Requeridos!$A$10:$A$20,_Requeridos!$U$10:$U$20,"")="SI",AB23=""),"Centro de Costo",""),IF(AND(_xlfn.XLOOKUP($C$14,_Requeridos!$A$10:$A$20,_Requeridos!$V$10:$V$20,"")="SI",AC23=""),"Número de personal",""),IF(AND(_xlfn.XLOOKUP($C$14,_Requeridos!$A$10:$A$20,_Requeridos!$W$10:$W$20,"")="SI",AH23=""),"Valor Unitario","")),"✅ Completo"))
B24: 3 | G24: =IFERROR(_xlfn.XLOOKUP(F24,Clase!$C$2:$C$292,Clase!$B$2:$B$292,""),"") | AD24: =IFERROR(_xlfn.XLOOKUP(AB24,Ceco!$B$2:$B$901,Ceco!$C$2:$C$901,""),"") | AJ24: =IF(COUNTA(C24,D24,E24,F24,H24,I24,L24,M24,N24,P24,Q24,R24,S24,T24,U24,X24,Y24,Z24,AB24,AC24,AH24)=0,"",IF(LEN(_xlfn.TEXTJOIN(", ",TRUE,IF(AND(_xlfn.XLOOKUP($C$14,_Requeridos!$A$10:$A$20,_Requeridos!$B$10:$B$20,"")="SI",C24=""),"Orden de Inversión",""),IF(AND(_xlfn.XLOOKUP($C$14,_Requeridos!$A$10:$A$20,_Requeridos!$C$10:$C$20,"")="SI",D24=""),"Elemento PEP",""),IF(AND(_xlfn.XLOOKUP($C$14,_Requeridos!$A$10:$A$20,_Requeridos!$D$10:$D$20,"")="SI",E24=""),"Pedido",""),IF(AND(_xlfn.XLOOKUP($C$14,_Requeridos!$A$10:$A$20,_Requeridos!$E$10:$E$20,"")="SI",F24=""),"Descripción Activo SAP",""),IF(AND(_xlfn.XLOOKUP($C$14,_Requeridos!$A$10:$A$20,_Requeridos!$F$10:$F$20,"")="SI",G24=""),"Clase",""),IF(AND(_xlfn.XLOOKUP($C$14,_Requeridos!$A$10:$A$20,_Requeridos!$G$10:$G$20,"")="SI",H24=""),"Cantidad",""),IF(AND(_xlfn.XLOOKUP($C$14,_Requeridos!$A$10:$A$20,_Requeridos!$H$10:$H$20,"")="SI",I24=""),"Nombre principal AF",""),IF(AND(_xlfn.XLOOKUP($C$14,_Requeridos!$A$10:$A$20,_Requeridos!$I$10:$I$20,"")="SI",L24=""),"Fabricante",""),IF(AND(_xlfn.XLOOKUP($C$14,_Requeridos!$A$10:$A$20,_Requeridos!$J$10:$J$20,"")="SI",M24=""),"Nit Proveedor",""),IF(AND(_xlfn.XLOOKUP($C$14,_Requeridos!$A$10:$A$20,_Requeridos!$K$10:$K$20,"")="SI",N24=""),"Serie",""),IF(AND(_xlfn.XLOOKUP($C$14,_Requeridos!$A$10:$A$20,_Requeridos!$L$10:$L$20,"")="SI",P24=""),"Criterio Clas. 1",""),IF(AND(_xlfn.XLOOKUP($C$14,_Requeridos!$A$10:$A$20,_Requeridos!$M$10:$M$20,"")="SI",Q24=""),"Criterio Clas. 2",""),IF(AND(_xlfn.XLOOKUP($C$14,_Requeridos!$A$10:$A$20,_Requeridos!$N$10:$N$20,"")="SI",R24=""),"Criterio Clas. 3",""),IF(AND(_xlfn.XLOOKUP($C$14,_Requeridos!$A$10:$A$20,_Requeridos!$O$10:$O$20,"")="SI",S24=""),"Criterio Clas. 4",""),IF(AND(_xlfn.XLOOKUP($C$14,_Requeridos!$A$10:$A$20,_Requeridos!$P$10:$P$20,"")="SI",T24=""),"Criterio Clas. 5",""),IF(AND(_xlfn.XLOOKUP($C$14,_Requeridos!$A$10:$A$20,_Requeridos!$Q$10:$Q$20,"")="SI",U24=""),"Ubicación técnica",""),IF(AND(_xlfn.XLOOKUP($C$14,_Requeridos!$A$10:$A$20,_Requeridos!$R$10:$R$20,"")="SI",X24=""),"Centro",""),IF(AND(_xlfn.XLOOKUP($C$14,_Requeridos!$A$10:$A$20,_Requeridos!$S$10:$S$20,"")="SI",Y24=""),"Código País",""),IF(AND(_xlfn.XLOOKUP($C$14,_Requeridos!$A$10:$A$20,_Requeridos!$T$10:$T$20,"")="SI",Z24=""),"Emplazamiento",""),IF(AND(_xlfn.XLOOKUP($C$14,_Requeridos!$A$10:$A$20,_Requeridos!$U$10:$U$20,"")="SI",AB24=""),"Centro de Costo",""),IF(AND(_xlfn.XLOOKUP($C$14,_Requeridos!$A$10:$A$20,_Requeridos!$V$10:$V$20,"")="SI",AC24=""),"Número de personal",""),IF(AND(_xlfn.XLOOKUP($C$14,_Requeridos!$A$10:$A$20,_Requeridos!$W$10:$W$20,"")="SI",AH24=""),"Valor Unitario","")))>0,"⚠️ Faltan: "&_xlfn.TEXTJOIN(", ",TRUE,IF(AND(_xlfn.XLOOKUP($C$14,_Requeridos!$A$10:$A$20,_Requeridos!$B$10:$B$20,"")="SI",C24=""),"Orden de Inversión",""),IF(AND(_xlfn.XLOOKUP($C$14,_Requeridos!$A$10:$A$20,_Requeridos!$C$10:$C$20,"")="SI",D24=""),"Elemento PEP",""),IF(AND(_xlfn.XLOOKUP($C$14,_Requeridos!$A$10:$A$20,_Requeridos!$D$10:$D$20,"")="SI",E24=""),"Pedido",""),IF(AND(_xlfn.XLOOKUP($C$14,_Requeridos!$A$10:$A$20,_Requeridos!$E$10:$E$20,"")="SI",F24=""),"Descripción Activo SAP",""),IF(AND(_xlfn.XLOOKUP($C$14,_Requeridos!$A$10:$A$20,_Requeridos!$F$10:$F$20,"")="SI",G24=""),"Clase",""),IF(AND(_xlfn.XLOOKUP($C$14,_Requeridos!$A$10:$A$20,_Requeridos!$G$10:$G$20,"")="SI",H24=""),"Cantidad",""),IF(AND(_xlfn.XLOOKUP($C$14,_Requeridos!$A$10:$A$20,_Requeridos!$H$10:$H$20,"")="SI",I24=""),"Nombre principal AF",""),IF(AND(_xlfn.XLOOKUP($C$14,_Requeridos!$A$10:$A$20,_Requeridos!$I$10:$I$20,"")="SI",L24=""),"Fabricante",""),IF(AND(_xlfn.XLOOKUP($C$14,_Requeridos!$A$10:$A$20,_Requeridos!$J$10:$J$20,"")="SI",M24=""),"Nit Proveedor",""),IF(AND(_xlfn.XLOOKUP($C$14,_Requeridos!$A$10:$A$20,_Requeridos!$K$10:$K$20,"")="SI",N24=""),"Serie",""),IF(AND(_xlfn.XLOOKUP($C$14,_Requeridos!$A$10:$A$20,_Requeridos!$L$10:$L$20,"")="SI",P24=""),"Criterio Clas. 1",""),IF(AND(_xlfn.XLOOKUP($C$14,_Requeridos!$A$10:$A$20,_Requeridos!$M$10:$M$20,"")="SI",Q24=""),"Criterio Clas. 2",""),IF(AND(_xlfn.XLOOKUP($C$14,_Requeridos!$A$10:$A$20,_Requeridos!$N$10:$N$20,"")="SI",R24=""),"Criterio Clas. 3",""),IF(AND(_xlfn.XLOOKUP($C$14,_Requeridos!$A$10:$A$20,_Requeridos!$O$10:$O$20,"")="SI",S24=""),"Criterio Clas. 4",""),IF(AND(_xlfn.XLOOKUP($C$14,_Requeridos!$A$10:$A$20,_Requeridos!$P$10:$P$20,"")="SI",T24=""),"Criterio Clas. 5",""),IF(AND(_xlfn.XLOOKUP($C$14,_Requeridos!$A$10:$A$20,_Requeridos!$Q$10:$Q$20,"")="SI",U24=""),"Ubicación técnica",""),IF(AND(_xlfn.XLOOKUP($C$14,_Requeridos!$A$10:$A$20,_Requeridos!$R$10:$R$20,"")="SI",X24=""),"Centro",""),IF(AND(_xlfn.XLOOKUP($C$14,_Requeridos!$A$10:$A$20,_Requeridos!$S$10:$S$20,"")="SI",Y24=""),"Código País",""),IF(AND(_xlfn.XLOOKUP($C$14,_Requeridos!$A$10:$A$20,_Requeridos!$T$10:$T$20,"")="SI",Z24=""),"Emplazamiento",""),IF(AND(_xlfn.XLOOKUP($C$14,_Requeridos!$A$10:$A$20,_Requeridos!$U$10:$U$20,"")="SI",AB24=""),"Centro de Costo",""),IF(AND(_xlfn.XLOOKUP($C$14,_Requeridos!$A$10:$A$20,_Requeridos!$V$10:$V$20,"")="SI",AC24=""),"Número de personal",""),IF(AND(_xlfn.XLOOKUP($C$14,_Requeridos!$A$10:$A$20,_Requeridos!$W$10:$W$20,"")="SI",AH24=""),"Valor Unitario","")),"✅ Completo"))
B25: 4 | G25: =IFERROR(_xlfn.XLOOKUP(F25,Clase!$C$2:$C$292,Clase!$B$2:$B$292,""),"") | AD25: =IFERROR(_xlfn.XLOOKUP(AB25,Ceco!$B$2:$B$901,Ceco!$C$2:$C$901,""),"") | AJ25: =IF(COUNTA(C25,D25,E25,F25,H25,I25,L25,M25,N25,P25,Q25,R25,S25,T25,U25,X25,Y25,Z25,AB25,AC25,AH25)=0,"",IF(LEN(_xlfn.TEXTJOIN(", ",TRUE,IF(AND(_xlfn.XLOOKUP($C$14,_Requeridos!$A$10:$A$20,_Requeridos!$B$10:$B$20,"")="SI",C25=""),"Orden de Inversión",""),IF(AND(_xlfn.XLOOKUP($C$14,_Requeridos!$A$10:$A$20,_Requeridos!$C$10:$C$20,"")="SI",D25=""),"Elemento PEP",""),IF(AND(_xlfn.XLOOKUP($C$14,_Requeridos!$A$10:$A$20,_Requeridos!$D$10:$D$20,"")="SI",E25=""),"Pedido",""),IF(AND(_xlfn.XLOOKUP($C$14,_Requeridos!$A$10:$A$20,_Requeridos!$E$10:$E$20,"")="SI",F25=""),"Descripción Activo SAP",""),IF(AND(_xlfn.XLOOKUP($C$14,_Requeridos!$A$10:$A$20,_Requeridos!$F$10:$F$20,"")="SI",G25=""),"Clase",""),IF(AND(_xlfn.XLOOKUP($C$14,_Requeridos!$A$10:$A$20,_Requeridos!$G$10:$G$20,"")="SI",H25=""),"Cantidad",""),IF(AND(_xlfn.XLOOKUP($C$14,_Requeridos!$A$10:$A$20,_Requeridos!$H$10:$H$20,"")="SI",I25=""),"Nombre principal AF",""),IF(AND(_xlfn.XLOOKUP($C$14,_Requeridos!$A$10:$A$20,_Requeridos!$I$10:$I$20,"")="SI",L25=""),"Fabricante",""),IF(AND(_xlfn.XLOOKUP($C$14,_Requeridos!$A$10:$A$20,_Requeridos!$J$10:$J$20,"")="SI",M25=""),"Nit Proveedor",""),IF(AND(_xlfn.XLOOKUP($C$14,_Requeridos!$A$10:$A$20,_Requeridos!$K$10:$K$20,"")="SI",N25=""),"Serie",""),IF(AND(_xlfn.XLOOKUP($C$14,_Requeridos!$A$10:$A$20,_Requeridos!$L$10:$L$20,"")="SI",P25=""),"Criterio Clas. 1",""),IF(AND(_xlfn.XLOOKUP($C$14,_Requeridos!$A$10:$A$20,_Requeridos!$M$10:$M$20,"")="SI",Q25=""),"Criterio Clas. 2",""),IF(AND(_xlfn.XLOOKUP($C$14,_Requeridos!$A$10:$A$20,_Requeridos!$N$10:$N$20,"")="SI",R25=""),"Criterio Clas. 3",""),IF(AND(_xlfn.XLOOKUP($C$14,_Requeridos!$A$10:$A$20,_Requeridos!$O$10:$O$20,"")="SI",S25=""),"Criterio Clas. 4",""),IF(AND(_xlfn.XLOOKUP($C$14,_Requeridos!$A$10:$A$20,_Requeridos!$P$10:$P$20,"")="SI",T25=""),"Criterio Clas. 5",""),IF(AND(_xlfn.XLOOKUP($C$14,_Requeridos!$A$10:$A$20,_Requeridos!$Q$10:$Q$20,"")="SI",U25=""),"Ubicación técnica",""),IF(AND(_xlfn.XLOOKUP($C$14,_Requeridos!$A$10:$A$20,_Requeridos!$R$10:$R$20,"")="SI",X25=""),"Centro",""),IF(AND(_xlfn.XLOOKUP($C$14,_Requeridos!$A$10:$A$20,_Requeridos!$S$10:$S$20,"")="SI",Y25=""),"Código País",""),IF(AND(_xlfn.XLOOKUP($C$14,_Requeridos!$A$10:$A$20,_Requeridos!$T$10:$T$20,"")="SI",Z25=""),"Emplazamiento",""),IF(AND(_xlfn.XLOOKUP($C$14,_Requeridos!$A$10:$A$20,_Requeridos!$U$10:$U$20,"")="SI",AB25=""),"Centro de Costo",""),IF(AND(_xlfn.XLOOKUP($C$14,_Requeridos!$A$10:$A$20,_Requeridos!$V$10:$V$20,"")="SI",AC25=""),"Número de personal",""),IF(AND(_xlfn.XLOOKUP($C$14,_Requeridos!$A$10:$A$20,_Requeridos!$W$10:$W$20,"")="SI",AH25=""),"Valor Unitario","")))>0,"⚠️ Faltan: "&_xlfn.TEXTJOIN(", ",TRUE,IF(AND(_xlfn.XLOOKUP($C$14,_Requeridos!$A$10:$A$20,_Requeridos!$B$10:$B$20,"")="SI",C25=""),"Orden de Inversión",""),IF(AND(_xlfn.XLOOKUP($C$14,_Requeridos!$A$10:$A$20,_Requeridos!$C$10:$C$20,"")="SI",D25=""),"Elemento PEP",""),IF(AND(_xlfn.XLOOKUP($C$14,_Requeridos!$A$10:$A$20,_Requeridos!$D$10:$D$20,"")="SI",E25=""),"Pedido",""),IF(AND(_xlfn.XLOOKUP($C$14,_Requeridos!$A$10:$A$20,_Requeridos!$E$10:$E$20,"")="SI",F25=""),"Descripción Activo SAP",""),IF(AND(_xlfn.XLOOKUP($C$14,_Requeridos!$A$10:$A$20,_Requeridos!$F$10:$F$20,"")="SI",G25=""),"Clase",""),IF(AND(_xlfn.XLOOKUP($C$14,_Requeridos!$A$10:$A$20,_Requeridos!$G$10:$G$20,"")="SI",H25=""),"Cantidad",""),IF(AND(_xlfn.XLOOKUP($C$14,_Requeridos!$A$10:$A$20,_Requeridos!$H$10:$H$20,"")="SI",I25=""),"Nombre principal AF",""),IF(AND(_xlfn.XLOOKUP($C$14,_Requeridos!$A$10:$A$20,_Requeridos!$I$10:$I$20,"")="SI",L25=""),"Fabricante",""),IF(AND(_xlfn.XLOOKUP($C$14,_Requeridos!$A$10:$A$20,_Requeridos!$J$10:$J$20,"")="SI",M25=""),"Nit Proveedor",""),IF(AND(_xlfn.XLOOKUP($C$14,_Requeridos!$A$10:$A$20,_Requeridos!$K$10:$K$20,"")="SI",N25=""),"Serie",""),IF(AND(_xlfn.XLOOKUP($C$14,_Requeridos!$A$10:$A$20,_Requeridos!$L$10:$L$20,"")="SI",P25=""),"Criterio Clas. 1",""),IF(AND(_xlfn.XLOOKUP($C$14,_Requeridos!$A$10:$A$20,_Requeridos!$M$10:$M$20,"")="SI",Q25=""),"Criterio Clas. 2",""),IF(AND(_xlfn.XLOOKUP($C$14,_Requeridos!$A$10:$A$20,_Requeridos!$N$10:$N$20,"")="SI",R25=""),"Criterio Clas. 3",""),IF(AND(_xlfn.XLOOKUP($C$14,_Requeridos!$A$10:$A$20,_Requeridos!$O$10:$O$20,"")="SI",S25=""),"Criterio Clas. 4",""),IF(AND(_xlfn.XLOOKUP($C$14,_Requeridos!$A$10:$A$20,_Requeridos!$P$10:$P$20,"")="SI",T25=""),"Criterio Clas. 5",""),IF(AND(_xlfn.XLOOKUP($C$14,_Requeridos!$A$10:$A$20,_Requeridos!$Q$10:$Q$20,"")="SI",U25=""),"Ubicación técnica",""),IF(AND(_xlfn.XLOOKUP($C$14,_Requeridos!$A$10:$A$20,_Requeridos!$R$10:$R$20,"")="SI",X25=""),"Centro",""),IF(AND(_xlfn.XLOOKUP($C$14,_Requeridos!$A$10:$A$20,_Requeridos!$S$10:$S$20,"")="SI",Y25=""),"Código País",""),IF(AND(_xlfn.XLOOKUP($C$14,_Requeridos!$A$10:$A$20,_Requeridos!$T$10:$T$20,"")="SI",Z25=""),"Emplazamiento",""),IF(AND(_xlfn.XLOOKUP($C$14,_Requeridos!$A$10:$A$20,_Requeridos!$U$10:$U$20,"")="SI",AB25=""),"Centro de Costo",""),IF(AND(_xlfn.XLOOKUP($C$14,_Requeridos!$A$10:$A$20,_Requeridos!$V$10:$V$20,"")="SI",AC25=""),"Número de personal",""),IF(AND(_xlfn.XLOOKUP($C$14,_Requeridos!$A$10:$A$20,_Requeridos!$W$10:$W$20,"")="SI",AH25=""),"Valor Unitario","")),"✅ Completo"))
B26: 5 | G26: =IFERROR(_xlfn.XLOOKUP(F26,Clase!$C$2:$C$292,Clase!$B$2:$B$292,""),"") | AD26: =IFERROR(_xlfn.XLOOKUP(AB26,Ceco!$B$2:$B$901,Ceco!$C$2:$C$901,""),"") | AJ26: =IF(COUNTA(C26,D26,E26,F26,H26,I26,L26,M26,N26,P26,Q26,R26,S26,T26,U26,X26,Y26,Z26,AB26,AC26,AH26)=0,"",IF(LEN(_xlfn.TEXTJOIN(", ",TRUE,IF(AND(_xlfn.XLOOKUP($C$14,_Requeridos!$A$10:$A$20,_Requeridos!$B$10:$B$20,"")="SI",C26=""),"Orden de Inversión",""),IF(AND(_xlfn.XLOOKUP($C$14,_Requeridos!$A$10:$A$20,_Requeridos!$C$10:$C$20,"")="SI",D26=""),"Elemento PEP",""),IF(AND(_xlfn.XLOOKUP($C$14,_Requeridos!$A$10:$A$20,_Requeridos!$D$10:$D$20,"")="SI",E26=""),"Pedido",""),IF(AND(_xlfn.XLOOKUP($C$14,_Requeridos!$A$10:$A$20,_Requeridos!$E$10:$E$20,"")="SI",F26=""),"Descripción Activo SAP",""),IF(AND(_xlfn.XLOOKUP($C$14,_Requeridos!$A$10:$A$20,_Requeridos!$F$10:$F$20,"")="SI",G26=""),"Clase",""),IF(AND(_xlfn.XLOOKUP($C$14,_Requeridos!$A$10:$A$20,_Requeridos!$G$10:$G$20,"")="SI",H26=""),"Cantidad",""),IF(AND(_xlfn.XLOOKUP($C$14,_Requeridos!$A$10:$A$20,_Requeridos!$H$10:$H$20,"")="SI",I26=""),"Nombre principal AF",""),IF(AND(_xlfn.XLOOKUP($C$14,_Requeridos!$A$10:$A$20,_Requeridos!$I$10:$I$20,"")="SI",L26=""),"Fabricante",""),IF(AND(_xlfn.XLOOKUP($C$14,_Requeridos!$A$10:$A$20,_Requeridos!$J$10:$J$20,"")="SI",M26=""),"Nit Proveedor",""),IF(AND(_xlfn.XLOOKUP($C$14,_Requeridos!$A$10:$A$20,_Requeridos!$K$10:$K$20,"")="SI",N26=""),"Serie",""),IF(AND(_xlfn.XLOOKUP($C$14,_Requeridos!$A$10:$A$20,_Requeridos!$L$10:$L$20,"")="SI",P26=""),"Criterio Clas. 1",""),IF(AND(_xlfn.XLOOKUP($C$14,_Requeridos!$A$10:$A$20,_Requeridos!$M$10:$M$20,"")="SI",Q26=""),"Criterio Clas. 2",""),IF(AND(_xlfn.XLOOKUP($C$14,_Requeridos!$A$10:$A$20,_Requeridos!$N$10:$N$20,"")="SI",R26=""),"Criterio Clas. 3",""),IF(AND(_xlfn.XLOOKUP($C$14,_Requeridos!$A$10:$A$20,_Requeridos!$O$10:$O$20,"")="SI",S26=""),"Criterio Clas. 4",""),IF(AND(_xlfn.XLOOKUP($C$14,_Requeridos!$A$10:$A$20,_Requeridos!$P$10:$P$20,"")="SI",T26=""),"Criterio Clas. 5",""),IF(AND(_xlfn.XLOOKUP($C$14,_Requeridos!$A$10:$A$20,_Requeridos!$Q$10:$Q$20,"")="SI",U26=""),"Ubicación técnica",""),IF(AND(_xlfn.XLOOKUP($C$14,_Requeridos!$A$10:$A$20,_Requeridos!$R$10:$R$20,"")="SI",X26=""),"Centro",""),IF(AND(_xlfn.XLOOKUP($C$14,_Requeridos!$A$10:$A$20,_Requeridos!$S$10:$S$20,"")="SI",Y26=""),"Código País",""),IF(AND(_xlfn.XLOOKUP($C$14,_Requeridos!$A$10:$A$20,_Requeridos!$T$10:$T$20,"")="SI",Z26=""),"Emplazamiento",""),IF(AND(_xlfn.XLOOKUP($C$14,_Requeridos!$A$10:$A$20,_Requeridos!$U$10:$U$20,"")="SI",AB26=""),"Centro de Costo",""),IF(AND(_xlfn.XLOOKUP($C$14,_Requeridos!$A$10:$A$20,_Requeridos!$V$10:$V$20,"")="SI",AC26=""),"Número de personal",""),IF(AND(_xlfn.XLOOKUP($C$14,_Requeridos!$A$10:$A$20,_Requeridos!$W$10:$W$20,"")="SI",AH26=""),"Valor Unitario","")))>0,"⚠️ Faltan: "&_xlfn.TEXTJOIN(", ",TRUE,IF(AND(_xlfn.XLOOKUP($C$14,_Requeridos!$A$10:$A$20,_Requeridos!$B$10:$B$20,"")="SI",C26=""),"Orden de Inversión",""),IF(AND(_xlfn.XLOOKUP($C$14,_Requeridos!$A$10:$A$20,_Requeridos!$C$10:$C$20,"")="SI",D26=""),"Elemento PEP",""),IF(AND(_xlfn.XLOOKUP($C$14,_Requeridos!$A$10:$A$20,_Requeridos!$D$10:$D$20,"")="SI",E26=""),"Pedido",""),IF(AND(_xlfn.XLOOKUP($C$14,_Requeridos!$A$10:$A$20,_Requeridos!$E$10:$E$20,"")="SI",F26=""),"Descripción Activo SAP",""),IF(AND(_xlfn.XLOOKUP($C$14,_Requeridos!$A$10:$A$20,_Requeridos!$F$10:$F$20,"")="SI",G26=""),"Clase",""),IF(AND(_xlfn.XLOOKUP($C$14,_Requeridos!$A$10:$A$20,_Requeridos!$G$10:$G$20,"")="SI",H26=""),"Cantidad",""),IF(AND(_xlfn.XLOOKUP($C$14,_Requeridos!$A$10:$A$20,_Requeridos!$H$10:$H$20,"")="SI",I26=""),"Nombre principal AF",""),IF(AND(_xlfn.XLOOKUP($C$14,_Requeridos!$A$10:$A$20,_Requeridos!$I$10:$I$20,"")="SI",L26=""),"Fabricante",""),IF(AND(_xlfn.XLOOKUP($C$14,_Requeridos!$A$10:$A$20,_Requeridos!$J$10:$J$20,"")="SI",M26=""),"Nit Proveedor",""),IF(AND(_xlfn.XLOOKUP($C$14,_Requeridos!$A$10:$A$20,_Requeridos!$K$10:$K$20,"")="SI",N26=""),"Serie",""),IF(AND(_xlfn.XLOOKUP($C$14,_Requeridos!$A$10:$A$20,_Requeridos!$L$10:$L$20,"")="SI",P26=""),"Criterio Clas. 1",""),IF(AND(_xlfn.XLOOKUP($C$14,_Requeridos!$A$10:$A$20,_Requeridos!$M$10:$M$20,"")="SI",Q26=""),"Criterio Clas. 2",""),IF(AND(_xlfn.XLOOKUP($C$14,_Requeridos!$A$10:$A$20,_Requeridos!$N$10:$N$20,"")="SI",R26=""),"Criterio Clas. 3",""),IF(AND(_xlfn.XLOOKUP($C$14,_Requeridos!$A$10:$A$20,_Requeridos!$O$10:$O$20,"")="SI",S26=""),"Criterio Clas. 4",""),IF(AND(_xlfn.XLOOKUP($C$14,_Requeridos!$A$10:$A$20,_Requeridos!$P$10:$P$20,"")="SI",T26=""),"Criterio Clas. 5",""),IF(AND(_xlfn.XLOOKUP($C$14,_Requeridos!$A$10:$A$20,_Requeridos!$Q$10:$Q$20,"")="SI",U26=""),"Ubicación técnica",""),IF(AND(_xlfn.XLOOKUP($C$14,_Requeridos!$A$10:$A$20,_Requeridos!$R$10:$R$20,"")="SI",X26=""),"Centro",""),IF(AND(_xlfn.XLOOKUP($C$14,_Requeridos!$A$10:$A$20,_Requeridos!$S$10:$S$20,"")="SI",Y26=""),"Código País",""),IF(AND(_xlfn.XLOOKUP($C$14,_Requeridos!$A$10:$A$20,_Requeridos!$T$10:$T$20,"")="SI",Z26=""),"Emplazamiento",""),IF(AND(_xlfn.XLOOKUP($C$14,_Requeridos!$A$10:$A$20,_Requeridos!$U$10:$U$20,"")="SI",AB26=""),"Centro de Costo",""),IF(AND(_xlfn.XLOOKUP($C$14,_Requeridos!$A$10:$A$20,_Requeridos!$V$10:$V$20,"")="SI",AC26=""),"Número de personal",""),IF(AND(_xlfn.XLOOKUP($C$14,_Requeridos!$A$10:$A$20,_Requeridos!$W$10:$W$20,"")="SI",AH26=""),"Valor Unitario","")),"✅ Completo"))
B27: 6 | G27: =IFERROR(_xlfn.XLOOKUP(F27,Clase!$C$2:$C$292,Clase!$B$2:$B$292,""),"") | AD27: =IFERROR(_xlfn.XLOOKUP(AB27,Ceco!$B$2:$B$901,Ceco!$C$2:$C$901,""),"") | AJ27: =IF(COUNTA(C27,D27,E27,F27,H27,I27,L27,M27,N27,P27,Q27,R27,S27,T27,U27,X27,Y27,Z27,AB27,AC27,AH27)=0,"",IF(LEN(_xlfn.TEXTJOIN(", ",TRUE,IF(AND(_xlfn.XLOOKUP($C$14,_Requeridos!$A$10:$A$20,_Requeridos!$B$10:$B$20,"")="SI",C27=""),"Orden de Inversión",""),IF(AND(_xlfn.XLOOKUP($C$14,_Requeridos!$A$10:$A$20,_Requeridos!$C$10:$C$20,"")="SI",D27=""),"Elemento PEP",""),IF(AND(_xlfn.XLOOKUP($C$14,_Requeridos!$A$10:$A$20,_Requeridos!$D$10:$D$20,"")="SI",E27=""),"Pedido",""),IF(AND(_xlfn.XLOOKUP($C$14,_Requeridos!$A$10:$A$20,_Requeridos!$E$10:$E$20,"")="SI",F27=""),"Descripción Activo SAP",""),IF(AND(_xlfn.XLOOKUP($C$14,_Requeridos!$A$10:$A$20,_Requeridos!$F$10:$F$20,"")="SI",G27=""),"Clase",""),IF(AND(_xlfn.XLOOKUP($C$14,_Requeridos!$A$10:$A$20,_Requeridos!$G$10:$G$20,"")="SI",H27=""),"Cantidad",""),IF(AND(_xlfn.XLOOKUP($C$14,_Requeridos!$A$10:$A$20,_Requeridos!$H$10:$H$20,"")="SI",I27=""),"Nombre principal AF",""),IF(AND(_xlfn.XLOOKUP($C$14,_Requeridos!$A$10:$A$20,_Requeridos!$I$10:$I$20,"")="SI",L27=""),"Fabricante",""),IF(AND(_xlfn.XLOOKUP($C$14,_Requeridos!$A$10:$A$20,_Requeridos!$J$10:$J$20,"")="SI",M27=""),"Nit Proveedor",""),IF(AND(_xlfn.XLOOKUP($C$14,_Requeridos!$A$10:$A$20,_Requeridos!$K$10:$K$20,"")="SI",N27=""),"Serie",""),IF(AND(_xlfn.XLOOKUP($C$14,_Requeridos!$A$10:$A$20,_Requeridos!$L$10:$L$20,"")="SI",P27=""),"Criterio Clas. 1",""),IF(AND(_xlfn.XLOOKUP($C$14,_Requeridos!$A$10:$A$20,_Requeridos!$M$10:$M$20,"")="SI",Q27=""),"Criterio Clas. 2",""),IF(AND(_xlfn.XLOOKUP($C$14,_Requeridos!$A$10:$A$20,_Requeridos!$N$10:$N$20,"")="SI",R27=""),"Criterio Clas. 3",""),IF(AND(_xlfn.XLOOKUP($C$14,_Requeridos!$A$10:$A$20,_Requeridos!$O$10:$O$20,"")="SI",S27=""),"Criterio Clas. 4",""),IF(AND(_xlfn.XLOOKUP($C$14,_Requeridos!$A$10:$A$20,_Requeridos!$P$10:$P$20,"")="SI",T27=""),"Criterio Clas. 5",""),IF(AND(_xlfn.XLOOKUP($C$14,_Requeridos!$A$10:$A$20,_Requeridos!$Q$10:$Q$20,"")="SI",U27=""),"Ubicación técnica",""),IF(AND(_xlfn.XLOOKUP($C$14,_Requeridos!$A$10:$A$20,_Requeridos!$R$10:$R$20,"")="SI",X27=""),"Centro",""),IF(AND(_xlfn.XLOOKUP($C$14,_Requeridos!$A$10:$A$20,_Requeridos!$S$10:$S$20,"")="SI",Y27=""),"Código País",""),IF(AND(_xlfn.XLOOKUP($C$14,_Requeridos!$A$10:$A$20,_Requeridos!$T$10:$T$20,"")="SI",Z27=""),"Emplazamiento",""),IF(AND(_xlfn.XLOOKUP($C$14,_Requeridos!$A$10:$A$20,_Requeridos!$U$10:$U$20,"")="SI",AB27=""),"Centro de Costo",""),IF(AND(_xlfn.XLOOKUP($C$14,_Requeridos!$A$10:$A$20,_Requeridos!$V$10:$V$20,"")="SI",AC27=""),"Número de personal",""),IF(AND(_xlfn.XLOOKUP($C$14,_Requeridos!$A$10:$A$20,_Requeridos!$W$10:$W$20,"")="SI",AH27=""),"Valor Unitario","")))>0,"⚠️ Faltan: "&_xlfn.TEXTJOIN(", ",TRUE,IF(AND(_xlfn.XLOOKUP($C$14,_Requeridos!$A$10:$A$20,_Requeridos!$B$10:$B$20,"")="SI",C27=""),"Orden de Inversión",""),IF(AND(_xlfn.XLOOKUP($C$14,_Requeridos!$A$10:$A$20,_Requeridos!$C$10:$C$20,"")="SI",D27=""),"Elemento PEP",""),IF(AND(_xlfn.XLOOKUP($C$14,_Requeridos!$A$10:$A$20,_Requeridos!$D$10:$D$20,"")="SI",E27=""),"Pedido",""),IF(AND(_xlfn.XLOOKUP($C$14,_Requeridos!$A$10:$A$20,_Requeridos!$E$10:$E$20,"")="SI",F27=""),"Descripción Activo SAP",""),IF(AND(_xlfn.XLOOKUP($C$14,_Requeridos!$A$10:$A$20,_Requeridos!$F$10:$F$20,"")="SI",G27=""),"Clase",""),IF(AND(_xlfn.XLOOKUP($C$14,_Requeridos!$A$10:$A$20,_Requeridos!$G$10:$G$20,"")="SI",H27=""),"Cantidad",""),IF(AND(_xlfn.XLOOKUP($C$14,_Requeridos!$A$10:$A$20,_Requeridos!$H$10:$H$20,"")="SI",I27=""),"Nombre principal AF",""),IF(AND(_xlfn.XLOOKUP($C$14,_Requeridos!$A$10:$A$20,_Requeridos!$I$10:$I$20,"")="SI",L27=""),"Fabricante",""),IF(AND(_xlfn.XLOOKUP($C$14,_Requeridos!$A$10:$A$20,_Requeridos!$J$10:$J$20,"")="SI",M27=""),"Nit Proveedor",""),IF(AND(_xlfn.XLOOKUP($C$14,_Requeridos!$A$10:$A$20,_Requeridos!$K$10:$K$20,"")="SI",N27=""),"Serie",""),IF(AND(_xlfn.XLOOKUP($C$14,_Requeridos!$A$10:$A$20,_Requeridos!$L$10:$L$20,"")="SI",P27=""),"Criterio Clas. 1",""),IF(AND(_xlfn.XLOOKUP($C$14,_Requeridos!$A$10:$A$20,_Requeridos!$M$10:$M$20,"")="SI",Q27=""),"Criterio Clas. 2",""),IF(AND(_xlfn.XLOOKUP($C$14,_Requeridos!$A$10:$A$20,_Requeridos!$N$10:$N$20,"")="SI",R27=""),"Criterio Clas. 3",""),IF(AND(_xlfn.XLOOKUP($C$14,_Requeridos!$A$10:$A$20,_Requeridos!$O$10:$O$20,"")="SI",S27=""),"Criterio Clas. 4",""),IF(AND(_xlfn.XLOOKUP($C$14,_Requeridos!$A$10:$A$20,_Requeridos!$P$10:$P$20,"")="SI",T27=""),"Criterio Clas. 5",""),IF(AND(_xlfn.XLOOKUP($C$14,_Requeridos!$A$10:$A$20,_Requeridos!$Q$10:$Q$20,"")="SI",U27=""),"Ubicación técnica",""),IF(AND(_xlfn.XLOOKUP($C$14,_Requeridos!$A$10:$A$20,_Requeridos!$R$10:$R$20,"")="SI",X27=""),"Centro",""),IF(AND(_xlfn.XLOOKUP($C$14,_Requeridos!$A$10:$A$20,_Requeridos!$S$10:$S$20,"")="SI",Y27=""),"Código País",""),IF(AND(_xlfn.XLOOKUP($C$14,_Requeridos!$A$10:$A$20,_Requeridos!$T$10:$T$20,"")="SI",Z27=""),"Emplazamiento",""),IF(AND(_xlfn.XLOOKUP($C$14,_Requeridos!$A$10:$A$20,_Requeridos!$U$10:$U$20,"")="SI",AB27=""),"Centro de Costo",""),IF(AND(_xlfn.XLOOKUP($C$14,_Requeridos!$A$10:$A$20,_Requeridos!$V$10:$V$20,"")="SI",AC27=""),"Número de personal",""),IF(AND(_xlfn.XLOOKUP($C$14,_Requeridos!$A$10:$A$20,_Requeridos!$W$10:$W$20,"")="SI",AH27=""),"Valor Unitario","")),"✅ Completo"))
B28: 7 | G28: =IFERROR(_xlfn.XLOOKUP(F28,Clase!$C$2:$C$292,Clase!$B$2:$B$292,""),"") | AD28: =IFERROR(_xlfn.XLOOKUP(AB28,Ceco!$B$2:$B$901,Ceco!$C$2:$C$901,""),"") | AJ28: =IF(COUNTA(C28,D28,E28,F28,H28,I28,L28,M28,N28,P28,Q28,R28,S28,T28,U28,X28,Y28,Z28,AB28,AC28,AH28)=0,"",IF(LEN(_xlfn.TEXTJOIN(", ",TRUE,IF(AND(_xlfn.XLOOKUP($C$14,_Requeridos!$A$10:$A$20,_Requeridos!$B$10:$B$20,"")="SI",C28=""),"Orden de Inversión",""),IF(AND(_xlfn.XLOOKUP($C$14,_Requeridos!$A$10:$A$20,_Requeridos!$C$10:$C$20,"")="SI",D28=""),"Elemento PEP",""),IF(AND(_xlfn.XLOOKUP($C$14,_Requeridos!$A$10:$A$20,_Requeridos!$D$10:$D$20,"")="SI",E28=""),"Pedido",""),IF(AND(_xlfn.XLOOKUP($C$14,_Requeridos!$A$10:$A$20,_Requeridos!$E$10:$E$20,"")="SI",F28=""),"Descripción Activo SAP",""),IF(AND(_xlfn.XLOOKUP($C$14,_Requeridos!$A$10:$A$20,_Requeridos!$F$10:$F$20,"")="SI",G28=""),"Clase",""),IF(AND(_xlfn.XLOOKUP($C$14,_Requeridos!$A$10:$A$20,_Requeridos!$G$10:$G$20,"")="SI",H28=""),"Cantidad",""),IF(AND(_xlfn.XLOOKUP($C$14,_Requeridos!$A$10:$A$20,_Requeridos!$H$10:$H$20,"")="SI",I28=""),"Nombre principal AF",""),IF(AND(_xlfn.XLOOKUP($C$14,_Requeridos!$A$10:$A$20,_Requeridos!$I$10:$I$20,"")="SI",L28=""),"Fabricante",""),IF(AND(_xlfn.XLOOKUP($C$14,_Requeridos!$A$10:$A$20,_Requeridos!$J$10:$J$20,"")="SI",M28=""),"Nit Proveedor",""),IF(AND(_xlfn.XLOOKUP($C$14,_Requeridos!$A$10:$A$20,_Requeridos!$K$10:$K$20,"")="SI",N28=""),"Serie",""),IF(AND(_xlfn.XLOOKUP($C$14,_Requeridos!$A$10:$A$20,_Requeridos!$L$10:$L$20,"")="SI",P28=""),"Criterio Clas. 1",""),IF(AND(_xlfn.XLOOKUP($C$14,_Requeridos!$A$10:$A$20,_Requeridos!$M$10:$M$20,"")="SI",Q28=""),"Criterio Clas. 2",""),IF(AND(_xlfn.XLOOKUP($C$14,_Requeridos!$A$10:$A$20,_Requeridos!$N$10:$N$20,"")="SI",R28=""),"Criterio Clas. 3",""),IF(AND(_xlfn.XLOOKUP($C$14,_Requeridos!$A$10:$A$20,_Requeridos!$O$10:$O$20,"")="SI",S28=""),"Criterio Clas. 4",""),IF(AND(_xlfn.XLOOKUP($C$14,_Requeridos!$A$10:$A$20,_Requeridos!$P$10:$P$20,"")="SI",T28=""),"Criterio Clas. 5",""),IF(AND(_xlfn.XLOOKUP($C$14,_Requeridos!$A$10:$A$20,_Requeridos!$Q$10:$Q$20,"")="SI",U28=""),"Ubicación técnica",""),IF(AND(_xlfn.XLOOKUP($C$14,_Requeridos!$A$10:$A$20,_Requeridos!$R$10:$R$20,"")="SI",X28=""),"Centro",""),IF(AND(_xlfn.XLOOKUP($C$14,_Requeridos!$A$10:$A$20,_Requeridos!$S$10:$S$20,"")="SI",Y28=""),"Código País",""),IF(AND(_xlfn.XLOOKUP($C$14,_Requeridos!$A$10:$A$20,_Requeridos!$T$10:$T$20,"")="SI",Z28=""),"Emplazamiento",""),IF(AND(_xlfn.XLOOKUP($C$14,_Requeridos!$A$10:$A$20,_Requeridos!$U$10:$U$20,"")="SI",AB28=""),"Centro de Costo",""),IF(AND(_xlfn.XLOOKUP($C$14,_Requeridos!$A$10:$A$20,_Requeridos!$V$10:$V$20,"")="SI",AC28=""),"Número de personal",""),IF(AND(_xlfn.XLOOKUP($C$14,_Requeridos!$A$10:$A$20,_Requeridos!$W$10:$W$20,"")="SI",AH28=""),"Valor Unitario","")))>0,"⚠️ Faltan: "&_xlfn.TEXTJOIN(", ",TRUE,IF(AND(_xlfn.XLOOKUP($C$14,_Requeridos!$A$10:$A$20,_Requeridos!$B$10:$B$20,"")="SI",C28=""),"Orden de Inversión",""),IF(AND(_xlfn.XLOOKUP($C$14,_Requeridos!$A$10:$A$20,_Requeridos!$C$10:$C$20,"")="SI",D28=""),"Elemento PEP",""),IF(AND(_xlfn.XLOOKUP($C$14,_Requeridos!$A$10:$A$20,_Requeridos!$D$10:$D$20,"")="SI",E28=""),"Pedido",""),IF(AND(_xlfn.XLOOKUP($C$14,_Requeridos!$A$10:$A$20,_Requeridos!$E$10:$E$20,"")="SI",F28=""),"Descripción Activo SAP",""),IF(AND(_xlfn.XLOOKUP($C$14,_Requeridos!$A$10:$A$20,_Requeridos!$F$10:$F$20,"")="SI",G28=""),"Clase",""),IF(AND(_xlfn.XLOOKUP($C$14,_Requeridos!$A$10:$A$20,_Requeridos!$G$10:$G$20,"")="SI",H28=""),"Cantidad",""),IF(AND(_xlfn.XLOOKUP($C$14,_Requeridos!$A$10:$A$20,_Requeridos!$H$10:$H$20,"")="SI",I28=""),"Nombre principal AF",""),IF(AND(_xlfn.XLOOKUP($C$14,_Requeridos!$A$10:$A$20,_Requeridos!$I$10:$I$20,"")="SI",L28=""),"Fabricante",""),IF(AND(_xlfn.XLOOKUP($C$14,_Requeridos!$A$10:$A$20,_Requeridos!$J$10:$J$20,"")="SI",M28=""),"Nit Proveedor",""),IF(AND(_xlfn.XLOOKUP($C$14,_Requeridos!$A$10:$A$20,_Requeridos!$K$10:$K$20,"")="SI",N28=""),"Serie",""),IF(AND(_xlfn.XLOOKUP($C$14,_Requeridos!$A$10:$A$20,_Requeridos!$L$10:$L$20,"")="SI",P28=""),"Criterio Clas. 1",""),IF(AND(_xlfn.XLOOKUP($C$14,_Requeridos!$A$10:$A$20,_Requeridos!$M$10:$M$20,"")="SI",Q28=""),"Criterio Clas. 2",""),IF(AND(_xlfn.XLOOKUP($C$14,_Requeridos!$A$10:$A$20,_Requeridos!$N$10:$N$20,"")="SI",R28=""),"Criterio Clas. 3",""),IF(AND(_xlfn.XLOOKUP($C$14,_Requeridos!$A$10:$A$20,_Requeridos!$O$10:$O$20,"")="SI",S28=""),"Criterio Clas. 4",""),IF(AND(_xlfn.XLOOKUP($C$14,_Requeridos!$A$10:$A$20,_Requeridos!$P$10:$P$20,"")="SI",T28=""),"Criterio Clas. 5",""),IF(AND(_xlfn.XLOOKUP($C$14,_Requeridos!$A$10:$A$20,_Requeridos!$Q$10:$Q$20,"")="SI",U28=""),"Ubicación técnica",""),IF(AND(_xlfn.XLOOKUP($C$14,_Requeridos!$A$10:$A$20,_Requeridos!$R$10:$R$20,"")="SI",X28=""),"Centro",""),IF(AND(_xlfn.XLOOKUP($C$14,_Requeridos!$A$10:$A$20,_Requeridos!$S$10:$S$20,"")="SI",Y28=""),"Código País",""),IF(AND(_xlfn.XLOOKUP($C$14,_Requeridos!$A$10:$A$20,_Requeridos!$T$10:$T$20,"")="SI",Z28=""),"Emplazamiento",""),IF(AND(_xlfn.XLOOKUP($C$14,_Requeridos!$A$10:$A$20,_Requeridos!$U$10:$U$20,"")="SI",AB28=""),"Centro de Costo",""),IF(AND(_xlfn.XLOOKUP($C$14,_Requeridos!$A$10:$A$20,_Requeridos!$V$10:$V$20,"")="SI",AC28=""),"Número de personal",""),IF(AND(_xlfn.XLOOKUP($C$14,_Requeridos!$A$10:$A$20,_Requeridos!$W$10:$W$20,"")="SI",AH28=""),"Valor Unitario","")),"✅ Completo"))
B29: 8 | G29: =IFERROR(_xlfn.XLOOKUP(F29,Clase!$C$2:$C$292,Clase!$B$2:$B$292,""),"") | AD29: =IFERROR(_xlfn.XLOOKUP(AB29,Ceco!$B$2:$B$901,Ceco!$C$2:$C$901,""),"") | AJ29: =IF(COUNTA(C29,D29,E29,F29,H29,I29,L29,M29,N29,P29,Q29,R29,S29,T29,U29,X29,Y29,Z29,AB29,AC29,AH29)=0,"",IF(LEN(_xlfn.TEXTJOIN(", ",TRUE,IF(AND(_xlfn.XLOOKUP($C$14,_Requeridos!$A$10:$A$20,_Requeridos!$B$10:$B$20,"")="SI",C29=""),"Orden de Inversión",""),IF(AND(_xlfn.XLOOKUP($C$14,_Requeridos!$A$10:$A$20,_Requeridos!$C$10:$C$20,"")="SI",D29=""),"Elemento PEP",""),IF(AND(_xlfn.XLOOKUP($C$14,_Requeridos!$A$10:$A$20,_Requeridos!$D$10:$D$20,"")="SI",E29=""),"Pedido",""),IF(AND(_xlfn.XLOOKUP($C$14,_Requeridos!$A$10:$A$20,_Requeridos!$E$10:$E$20,"")="SI",F29=""),"Descripción Activo SAP",""),IF(AND(_xlfn.XLOOKUP($C$14,_Requeridos!$A$10:$A$20,_Requeridos!$F$10:$F$20,"")="SI",G29=""),"Clase",""),IF(AND(_xlfn.XLOOKUP($C$14,_Requeridos!$A$10:$A$20,_Requeridos!$G$10:$G$20,"")="SI",H29=""),"Cantidad",""),IF(AND(_xlfn.XLOOKUP($C$14,_Requeridos!$A$10:$A$20,_Requeridos!$H$10:$H$20,"")="SI",I29=""),"Nombre principal AF",""),IF(AND(_xlfn.XLOOKUP($C$14,_Requeridos!$A$10:$A$20,_Requeridos!$I$10:$I$20,"")="SI",L29=""),"Fabricante",""),IF(AND(_xlfn.XLOOKUP($C$14,_Requeridos!$A$10:$A$20,_Requeridos!$J$10:$J$20,"")="SI",M29=""),"Nit Proveedor",""),IF(AND(_xlfn.XLOOKUP($C$14,_Requeridos!$A$10:$A$20,_Requeridos!$K$10:$K$20,"")="SI",N29=""),"Serie",""),IF(AND(_xlfn.XLOOKUP($C$14,_Requeridos!$A$10:$A$20,_Requeridos!$L$10:$L$20,"")="SI",P29=""),"Criterio Clas. 1",""),IF(AND(_xlfn.XLOOKUP($C$14,_Requeridos!$A$10:$A$20,_Requeridos!$M$10:$M$20,"")="SI",Q29=""),"Criterio Clas. 2",""),IF(AND(_xlfn.XLOOKUP($C$14,_Requeridos!$A$10:$A$20,_Requeridos!$N$10:$N$20,"")="SI",R29=""),"Criterio Clas. 3",""),IF(AND(_xlfn.XLOOKUP($C$14,_Requeridos!$A$10:$A$20,_Requeridos!$O$10:$O$20,"")="SI",S29=""),"Criterio Clas. 4",""),IF(AND(_xlfn.XLOOKUP($C$14,_Requeridos!$A$10:$A$20,_Requeridos!$P$10:$P$20,"")="SI",T29=""),"Criterio Clas. 5",""),IF(AND(_xlfn.XLOOKUP($C$14,_Requeridos!$A$10:$A$20,_Requeridos!$Q$10:$Q$20,"")="SI",U29=""),"Ubicación técnica",""),IF(AND(_xlfn.XLOOKUP($C$14,_Requeridos!$A$10:$A$20,_Requeridos!$R$10:$R$20,"")="SI",X29=""),"Centro",""),IF(AND(_xlfn.XLOOKUP($C$14,_Requeridos!$A$10:$A$20,_Requeridos!$S$10:$S$20,"")="SI",Y29=""),"Código País",""),IF(AND(_xlfn.XLOOKUP($C$14,_Requeridos!$A$10:$A$20,_Requeridos!$T$10:$T$20,"")="SI",Z29=""),"Emplazamiento",""),IF(AND(_xlfn.XLOOKUP($C$14,_Requeridos!$A$10:$A$20,_Requeridos!$U$10:$U$20,"")="SI",AB29=""),"Centro de Costo",""),IF(AND(_xlfn.XLOOKUP($C$14,_Requeridos!$A$10:$A$20,_Requeridos!$V$10:$V$20,"")="SI",AC29=""),"Número de personal",""),IF(AND(_xlfn.XLOOKUP($C$14,_Requeridos!$A$10:$A$20,_Requeridos!$W$10:$W$20,"")="SI",AH29=""),"Valor Unitario","")))>0,"⚠️ Faltan: "&_xlfn.TEXTJOIN(", ",TRUE,IF(AND(_xlfn.XLOOKUP($C$14,_Requeridos!$A$10:$A$20,_Requeridos!$B$10:$B$20,"")="SI",C29=""),"Orden de Inversión",""),IF(AND(_xlfn.XLOOKUP($C$14,_Requeridos!$A$10:$A$20,_Requeridos!$C$10:$C$20,"")="SI",D29=""),"Elemento PEP",""),IF(AND(_xlfn.XLOOKUP($C$14,_Requeridos!$A$10:$A$20,_Requeridos!$D$10:$D$20,"")="SI",E29=""),"Pedido",""),IF(AND(_xlfn.XLOOKUP($C$14,_Requeridos!$A$10:$A$20,_Requeridos!$E$10:$E$20,"")="SI",F29=""),"Descripción Activo SAP",""),IF(AND(_xlfn.XLOOKUP($C$14,_Requeridos!$A$10:$A$20,_Requeridos!$F$10:$F$20,"")="SI",G29=""),"Clase",""),IF(AND(_xlfn.XLOOKUP($C$14,_Requeridos!$A$10:$A$20,_Requeridos!$G$10:$G$20,"")="SI",H29=""),"Cantidad",""),IF(AND(_xlfn.XLOOKUP($C$14,_Requeridos!$A$10:$A$20,_Requeridos!$H$10:$H$20,"")="SI",I29=""),"Nombre principal AF",""),IF(AND(_xlfn.XLOOKUP($C$14,_Requeridos!$A$10:$A$20,_Requeridos!$I$10:$I$20,"")="SI",L29=""),"Fabricante",""),IF(AND(_xlfn.XLOOKUP($C$14,_Requeridos!$A$10:$A$20,_Requeridos!$J$10:$J$20,"")="SI",M29=""),"Nit Proveedor",""),IF(AND(_xlfn.XLOOKUP($C$14,_Requeridos!$A$10:$A$20,_Requeridos!$K$10:$K$20,"")="SI",N29=""),"Serie",""),IF(AND(_xlfn.XLOOKUP($C$14,_Requeridos!$A$10:$A$20,_Requeridos!$L$10:$L$20,"")="SI",P29=""),"Criterio Clas. 1",""),IF(AND(_xlfn.XLOOKUP($C$14,_Requeridos!$A$10:$A$20,_Requeridos!$M$10:$M$20,"")="SI",Q29=""),"Criterio Clas. 2",""),IF(AND(_xlfn.XLOOKUP($C$14,_Requeridos!$A$10:$A$20,_Requeridos!$N$10:$N$20,"")="SI",R29=""),"Criterio Clas. 3",""),IF(AND(_xlfn.XLOOKUP($C$14,_Requeridos!$A$10:$A$20,_Requeridos!$O$10:$O$20,"")="SI",S29=""),"Criterio Clas. 4",""),IF(AND(_xlfn.XLOOKUP($C$14,_Requeridos!$A$10:$A$20,_Requeridos!$P$10:$P$20,"")="SI",T29=""),"Criterio Clas. 5",""),IF(AND(_xlfn.XLOOKUP($C$14,_Requeridos!$A$10:$A$20,_Requeridos!$Q$10:$Q$20,"")="SI",U29=""),"Ubicación técnica",""),IF(AND(_xlfn.XLOOKUP($C$14,_Requeridos!$A$10:$A$20,_Requeridos!$R$10:$R$20,"")="SI",X29=""),"Centro",""),IF(AND(_xlfn.XLOOKUP($C$14,_Requeridos!$A$10:$A$20,_Requeridos!$S$10:$S$20,"")="SI",Y29=""),"Código País",""),IF(AND(_xlfn.XLOOKUP($C$14,_Requeridos!$A$10:$A$20,_Requeridos!$T$10:$T$20,"")="SI",Z29=""),"Emplazamiento",""),IF(AND(_xlfn.XLOOKUP($C$14,_Requeridos!$A$10:$A$20,_Requeridos!$U$10:$U$20,"")="SI",AB29=""),"Centro de Costo",""),IF(AND(_xlfn.XLOOKUP($C$14,_Requeridos!$A$10:$A$20,_Requeridos!$V$10:$V$20,"")="SI",AC29=""),"Número de personal",""),IF(AND(_xlfn.XLOOKUP($C$14,_Requeridos!$A$10:$A$20,_Requeridos!$W$10:$W$20,"")="SI",AH29=""),"Valor Unitario","")),"✅ Completo"))
B30: 9 | G30: =IFERROR(_xlfn.XLOOKUP(F30,Clase!$C$2:$C$292,Clase!$B$2:$B$292,""),"") | AD30: =IFERROR(_xlfn.XLOOKUP(AB30,Ceco!$B$2:$B$901,Ceco!$C$2:$C$901,""),"") | AJ30: =IF(COUNTA(C30,D30,E30,F30,H30,I30,L30,M30,N30,P30,Q30,R30,S30,T30,U30,X30,Y30,Z30,AB30,AC30,AH30)=0,"",IF(LEN(_xlfn.TEXTJOIN(", ",TRUE,IF(AND(_xlfn.XLOOKUP($C$14,_Requeridos!$A$10:$A$20,_Requeridos!$B$10:$B$20,"")="SI",C30=""),"Orden de Inversión",""),IF(AND(_xlfn.XLOOKUP($C$14,_Requeridos!$A$10:$A$20,_Requeridos!$C$10:$C$20,"")="SI",D30=""),"Elemento PEP",""),IF(AND(_xlfn.XLOOKUP($C$14,_Requeridos!$A$10:$A$20,_Requeridos!$D$10:$D$20,"")="SI",E30=""),"Pedido",""),IF(AND(_xlfn.XLOOKUP($C$14,_Requeridos!$A$10:$A$20,_Requeridos!$E$10:$E$20,"")="SI",F30=""),"Descripción Activo SAP",""),IF(AND(_xlfn.XLOOKUP($C$14,_Requeridos!$A$10:$A$20,_Requeridos!$F$10:$F$20,"")="SI",G30=""),"Clase",""),IF(AND(_xlfn.XLOOKUP($C$14,_Requeridos!$A$10:$A$20,_Requeridos!$G$10:$G$20,"")="SI",H30=""),"Cantidad",""),IF(AND(_xlfn.XLOOKUP($C$14,_Requeridos!$A$10:$A$20,_Requeridos!$H$10:$H$20,"")="SI",I30=""),"Nombre principal AF",""),IF(AND(_xlfn.XLOOKUP($C$14,_Requeridos!$A$10:$A$20,_Requeridos!$I$10:$I$20,"")="SI",L30=""),"Fabricante",""),IF(AND(_xlfn.XLOOKUP($C$14,_Requeridos!$A$10:$A$20,_Requeridos!$J$10:$J$20,"")="SI",M30=""),"Nit Proveedor",""),IF(AND(_xlfn.XLOOKUP($C$14,_Requeridos!$A$10:$A$20,_Requeridos!$K$10:$K$20,"")="SI",N30=""),"Serie",""),IF(AND(_xlfn.XLOOKUP($C$14,_Requeridos!$A$10:$A$20,_Requeridos!$L$10:$L$20,"")="SI",P30=""),"Criterio Clas. 1",""),IF(AND(_xlfn.XLOOKUP($C$14,_Requeridos!$A$10:$A$20,_Requeridos!$M$10:$M$20,"")="SI",Q30=""),"Criterio Clas. 2",""),IF(AND(_xlfn.XLOOKUP($C$14,_Requeridos!$A$10:$A$20,_Requeridos!$N$10:$N$20,"")="SI",R30=""),"Criterio Clas. 3",""),IF(AND(_xlfn.XLOOKUP($C$14,_Requeridos!$A$10:$A$20,_Requeridos!$O$10:$O$20,"")="SI",S30=""),"Criterio Clas. 4",""),IF(AND(_xlfn.XLOOKUP($C$14,_Requeridos!$A$10:$A$20,_Requeridos!$P$10:$P$20,"")="SI",T30=""),"Criterio Clas. 5",""),IF(AND(_xlfn.XLOOKUP($C$14,_Requeridos!$A$10:$A$20,_Requeridos!$Q$10:$Q$20,"")="SI",U30=""),"Ubicación técnica",""),IF(AND(_xlfn.XLOOKUP($C$14,_Requeridos!$A$10:$A$20,_Requeridos!$R$10:$R$20,"")="SI",X30=""),"Centro",""),IF(AND(_xlfn.XLOOKUP($C$14,_Requeridos!$A$10:$A$20,_Requeridos!$S$10:$S$20,"")="SI",Y30=""),"Código País",""),IF(AND(_xlfn.XLOOKUP($C$14,_Requeridos!$A$10:$A$20,_Requeridos!$T$10:$T$20,"")="SI",Z30=""),"Emplazamiento",""),IF(AND(_xlfn.XLOOKUP($C$14,_Requeridos!$A$10:$A$20,_Requeridos!$U$10:$U$20,"")="SI",AB30=""),"Centro de Costo",""),IF(AND(_xlfn.XLOOKUP($C$14,_Requeridos!$A$10:$A$20,_Requeridos!$V$10:$V$20,"")="SI",AC30=""),"Número de personal",""),IF(AND(_xlfn.XLOOKUP($C$14,_Requeridos!$A$10:$A$20,_Requeridos!$W$10:$W$20,"")="SI",AH30=""),"Valor Unitario","")))>0,"⚠️ Faltan: "&_xlfn.TEXTJOIN(", ",TRUE,IF(AND(_xlfn.XLOOKUP($C$14,_Requeridos!$A$10:$A$20,_Requeridos!$B$10:$B$20,"")="SI",C30=""),"Orden de Inversión",""),IF(AND(_xlfn.XLOOKUP($C$14,_Requeridos!$A$10:$A$20,_Requeridos!$C$10:$C$20,"")="SI",D30=""),"Elemento PEP",""),IF(AND(_xlfn.XLOOKUP($C$14,_Requeridos!$A$10:$A$20,_Requeridos!$D$10:$D$20,"")="SI",E30=""),"Pedido",""),IF(AND(_xlfn.XLOOKUP($C$14,_Requeridos!$A$10:$A$20,_Requeridos!$E$10:$E$20,"")="SI",F30=""),"Descripción Activo SAP",""),IF(AND(_xlfn.XLOOKUP($C$14,_Requeridos!$A$10:$A$20,_Requeridos!$F$10:$F$20,"")="SI",G30=""),"Clase",""),IF(AND(_xlfn.XLOOKUP($C$14,_Requeridos!$A$10:$A$20,_Requeridos!$G$10:$G$20,"")="SI",H30=""),"Cantidad",""),IF(AND(_xlfn.XLOOKUP($C$14,_Requeridos!$A$10:$A$20,_Requeridos!$H$10:$H$20,"")="SI",I30=""),"Nombre principal AF",""),IF(AND(_xlfn.XLOOKUP($C$14,_Requeridos!$A$10:$A$20,_Requeridos!$I$10:$I$20,"")="SI",L30=""),"Fabricante",""),IF(AND(_xlfn.XLOOKUP($C$14,_Requeridos!$A$10:$A$20,_Requeridos!$J$10:$J$20,"")="SI",M30=""),"Nit Proveedor",""),IF(AND(_xlfn.XLOOKUP($C$14,_Requeridos!$A$10:$A$20,_Requeridos!$K$10:$K$20,"")="SI",N30=""),"Serie",""),IF(AND(_xlfn.XLOOKUP($C$14,_Requeridos!$A$10:$A$20,_Requeridos!$L$10:$L$20,"")="SI",P30=""),"Criterio Clas. 1",""),IF(AND(_xlfn.XLOOKUP($C$14,_Requeridos!$A$10:$A$20,_Requeridos!$M$10:$M$20,"")="SI",Q30=""),"Criterio Clas. 2",""),IF(AND(_xlfn.XLOOKUP($C$14,_Requeridos!$A$10:$A$20,_Requeridos!$N$10:$N$20,"")="SI",R30=""),"Criterio Clas. 3",""),IF(AND(_xlfn.XLOOKUP($C$14,_Requeridos!$A$10:$A$20,_Requeridos!$O$10:$O$20,"")="SI",S30=""),"Criterio Clas. 4",""),IF(AND(_xlfn.XLOOKUP($C$14,_Requeridos!$A$10:$A$20,_Requeridos!$P$10:$P$20,"")="SI",T30=""),"Criterio Clas. 5",""),IF(AND(_xlfn.XLOOKUP($C$14,_Requeridos!$A$10:$A$20,_Requeridos!$Q$10:$Q$20,"")="SI",U30=""),"Ubicación técnica",""),IF(AND(_xlfn.XLOOKUP($C$14,_Requeridos!$A$10:$A$20,_Requeridos!$R$10:$R$20,"")="SI",X30=""),"Centro",""),IF(AND(_xlfn.XLOOKUP($C$14,_Requeridos!$A$10:$A$20,_Requeridos!$S$10:$S$20,"")="SI",Y30=""),"Código País",""),IF(AND(_xlfn.XLOOKUP($C$14,_Requeridos!$A$10:$A$20,_Requeridos!$T$10:$T$20,"")="SI",Z30=""),"Emplazamiento",""),IF(AND(_xlfn.XLOOKUP($C$14,_Requeridos!$A$10:$A$20,_Requeridos!$U$10:$U$20,"")="SI",AB30=""),"Centro de Costo",""),IF(AND(_xlfn.XLOOKUP($C$14,_Requeridos!$A$10:$A$20,_Requeridos!$V$10:$V$20,"")="SI",AC30=""),"Número de personal",""),IF(AND(_xlfn.XLOOKUP($C$14,_Requeridos!$A$10:$A$20,_Requeridos!$W$10:$W$20,"")="SI",AH30=""),"Valor Unitario","")),"✅ Completo"))
B31: 10 | G31: =IFERROR(_xlfn.XLOOKUP(F31,Clase!$C$2:$C$292,Clase!$B$2:$B$292,""),"") | AD31: =IFERROR(_xlfn.XLOOKUP(AB31,Ceco!$B$2:$B$901,Ceco!$C$2:$C$901,""),"") | AJ31: =IF(COUNTA(C31,D31,E31,F31,H31,I31,L31,M31,N31,P31,Q31,R31,S31,T31,U31,X31,Y31,Z31,AB31,AC31,AH31)=0,"",IF(LEN(_xlfn.TEXTJOIN(", ",TRUE,IF(AND(_xlfn.XLOOKUP($C$14,_Requeridos!$A$10:$A$20,_Requeridos!$B$10:$B$20,"")="SI",C31=""),"Orden de Inversión",""),IF(AND(_xlfn.XLOOKUP($C$14,_Requeridos!$A$10:$A$20,_Requeridos!$C$10:$C$20,"")="SI",D31=""),"Elemento PEP",""),IF(AND(_xlfn.XLOOKUP($C$14,_Requeridos!$A$10:$A$20,_Requeridos!$D$10:$D$20,"")="SI",E31=""),"Pedido",""),IF(AND(_xlfn.XLOOKUP($C$14,_Requeridos!$A$10:$A$20,_Requeridos!$E$10:$E$20,"")="SI",F31=""),"Descripción Activo SAP",""),IF(AND(_xlfn.XLOOKUP($C$14,_Requeridos!$A$10:$A$20,_Requeridos!$F$10:$F$20,"")="SI",G31=""),"Clase",""),IF(AND(_xlfn.XLOOKUP($C$14,_Requeridos!$A$10:$A$20,_Requeridos!$G$10:$G$20,"")="SI",H31=""),"Cantidad",""),IF(AND(_xlfn.XLOOKUP($C$14,_Requeridos!$A$10:$A$20,_Requeridos!$H$10:$H$20,"")="SI",I31=""),"Nombre principal AF",""),IF(AND(_xlfn.XLOOKUP($C$14,_Requeridos!$A$10:$A$20,_Requeridos!$I$10:$I$20,"")="SI",L31=""),"Fabricante",""),IF(AND(_xlfn.XLOOKUP($C$14,_Requeridos!$A$10:$A$20,_Requeridos!$J$10:$J$20,"")="SI",M31=""),"Nit Proveedor",""),IF(AND(_xlfn.XLOOKUP($C$14,_Requeridos!$A$10:$A$20,_Requeridos!$K$10:$K$20,"")="SI",N31=""),"Serie",""),IF(AND(_xlfn.XLOOKUP($C$14,_Requeridos!$A$10:$A$20,_Requeridos!$L$10:$L$20,"")="SI",P31=""),"Criterio Clas. 1",""),IF(AND(_xlfn.XLOOKUP($C$14,_Requeridos!$A$10:$A$20,_Requeridos!$M$10:$M$20,"")="SI",Q31=""),"Criterio Clas. 2",""),IF(AND(_xlfn.XLOOKUP($C$14,_Requeridos!$A$10:$A$20,_Requeridos!$N$10:$N$20,"")="SI",R31=""),"Criterio Clas. 3",""),IF(AND(_xlfn.XLOOKUP($C$14,_Requeridos!$A$10:$A$20,_Requeridos!$O$10:$O$20,"")="SI",S31=""),"Criterio Clas. 4",""),IF(AND(_xlfn.XLOOKUP($C$14,_Requeridos!$A$10:$A$20,_Requeridos!$P$10:$P$20,"")="SI",T31=""),"Criterio Clas. 5",""),IF(AND(_xlfn.XLOOKUP($C$14,_Requeridos!$A$10:$A$20,_Requeridos!$Q$10:$Q$20,"")="SI",U31=""),"Ubicación técnica",""),IF(AND(_xlfn.XLOOKUP($C$14,_Requeridos!$A$10:$A$20,_Requeridos!$R$10:$R$20,"")="SI",X31=""),"Centro",""),IF(AND(_xlfn.XLOOKUP($C$14,_Requeridos!$A$10:$A$20,_Requeridos!$S$10:$S$20,"")="SI",Y31=""),"Código País",""),IF(AND(_xlfn.XLOOKUP($C$14,_Requeridos!$A$10:$A$20,_Requeridos!$T$10:$T$20,"")="SI",Z31=""),"Emplazamiento",""),IF(AND(_xlfn.XLOOKUP($C$14,_Requeridos!$A$10:$A$20,_Requeridos!$U$10:$U$20,"")="SI",AB31=""),"Centro de Costo",""),IF(AND(_xlfn.XLOOKUP($C$14,_Requeridos!$A$10:$A$20,_Requeridos!$V$10:$V$20,"")="SI",AC31=""),"Número de personal",""),IF(AND(_xlfn.XLOOKUP($C$14,_Requeridos!$A$10:$A$20,_Requeridos!$W$10:$W$20,"")="SI",AH31=""),"Valor Unitario","")))>0,"⚠️ Faltan: "&_xlfn.TEXTJOIN(", ",TRUE,IF(AND(_xlfn.XLOOKUP($C$14,_Requeridos!$A$10:$A$20,_Requeridos!$B$10:$B$20,"")="SI",C31=""),"Orden de Inversión",""),IF(AND(_xlfn.XLOOKUP($C$14,_Requeridos!$A$10:$A$20,_Requeridos!$C$10:$C$20,"")="SI",D31=""),"Elemento PEP",""),IF(AND(_xlfn.XLOOKUP($C$14,_Requeridos!$A$10:$A$20,_Requeridos!$D$10:$D$20,"")="SI",E31=""),"Pedido",""),IF(AND(_xlfn.XLOOKUP($C$14,_Requeridos!$A$10:$A$20,_Requeridos!$E$10:$E$20,"")="SI",F31=""),"Descripción Activo SAP",""),IF(AND(_xlfn.XLOOKUP($C$14,_Requeridos!$A$10:$A$20,_Requeridos!$F$10:$F$20,"")="SI",G31=""),"Clase",""),IF(AND(_xlfn.XLOOKUP($C$14,_Requeridos!$A$10:$A$20,_Requeridos!$G$10:$G$20,"")="SI",H31=""),"Cantidad",""),IF(AND(_xlfn.XLOOKUP($C$14,_Requeridos!$A$10:$A$20,_Requeridos!$H$10:$H$20,"")="SI",I31=""),"Nombre principal AF",""),IF(AND(_xlfn.XLOOKUP($C$14,_Requeridos!$A$10:$A$20,_Requeridos!$I$10:$I$20,"")="SI",L31=""),"Fabricante",""),IF(AND(_xlfn.XLOOKUP($C$14,_Requeridos!$A$10:$A$20,_Requeridos!$J$10:$J$20,"")="SI",M31=""),"Nit Proveedor",""),IF(AND(_xlfn.XLOOKUP($C$14,_Requeridos!$A$10:$A$20,_Requeridos!$K$10:$K$20,"")="SI",N31=""),"Serie",""),IF(AND(_xlfn.XLOOKUP($C$14,_Requeridos!$A$10:$A$20,_Requeridos!$L$10:$L$20,"")="SI",P31=""),"Criterio Clas. 1",""),IF(AND(_xlfn.XLOOKUP($C$14,_Requeridos!$A$10:$A$20,_Requeridos!$M$10:$M$20,"")="SI",Q31=""),"Criterio Clas. 2",""),IF(AND(_xlfn.XLOOKUP($C$14,_Requeridos!$A$10:$A$20,_Requeridos!$N$10:$N$20,"")="SI",R31=""),"Criterio Clas. 3",""),IF(AND(_xlfn.XLOOKUP($C$14,_Requeridos!$A$10:$A$20,_Requeridos!$O$10:$O$20,"")="SI",S31=""),"Criterio Clas. 4",""),IF(AND(_xlfn.XLOOKUP($C$14,_Requeridos!$A$10:$A$20,_Requeridos!$P$10:$P$20,"")="SI",T31=""),"Criterio Clas. 5",""),IF(AND(_xlfn.XLOOKUP($C$14,_Requeridos!$A$10:$A$20,_Requeridos!$Q$10:$Q$20,"")="SI",U31=""),"Ubicación técnica",""),IF(AND(_xlfn.XLOOKUP($C$14,_Requeridos!$A$10:$A$20,_Requeridos!$R$10:$R$20,"")="SI",X31=""),"Centro",""),IF(AND(_xlfn.XLOOKUP($C$14,_Requeridos!$A$10:$A$20,_Requeridos!$S$10:$S$20,"")="SI",Y31=""),"Código País",""),IF(AND(_xlfn.XLOOKUP($C$14,_Requeridos!$A$10:$A$20,_Requeridos!$T$10:$T$20,"")="SI",Z31=""),"Emplazamiento",""),IF(AND(_xlfn.XLOOKUP($C$14,_Requeridos!$A$10:$A$20,_Requeridos!$U$10:$U$20,"")="SI",AB31=""),"Centro de Costo",""),IF(AND(_xlfn.XLOOKUP($C$14,_Requeridos!$A$10:$A$20,_Requeridos!$V$10:$V$20,"")="SI",AC31=""),"Número de personal",""),IF(AND(_xlfn.XLOOKUP($C$14,_Requeridos!$A$10:$A$20,_Requeridos!$W$10:$W$20,"")="SI",AH31=""),"Valor Unitario","")),"✅ Completo"))
B32: 11 | G32: =IFERROR(_xlfn.XLOOKUP(F32,Clase!$C$2:$C$292,Clase!$B$2:$B$292,""),"") | AD32: =IFERROR(_xlfn.XLOOKUP(AB32,Ceco!$B$2:$B$901,Ceco!$C$2:$C$901,""),"") | AJ32: =IF(COUNTA(C32,D32,E32,F32,H32,I32,L32,M32,N32,P32,Q32,R32,S32,T32,U32,X32,Y32,Z32,AB32,AC32,AH32)=0,"",IF(LEN(_xlfn.TEXTJOIN(", ",TRUE,IF(AND(_xlfn.XLOOKUP($C$14,_Requeridos!$A$10:$A$20,_Requeridos!$B$10:$B$20,"")="SI",C32=""),"Orden de Inversión",""),IF(AND(_xlfn.XLOOKUP($C$14,_Requeridos!$A$10:$A$20,_Requeridos!$C$10:$C$20,"")="SI",D32=""),"Elemento PEP",""),IF(AND(_xlfn.XLOOKUP($C$14,_Requeridos!$A$10:$A$20,_Requeridos!$D$10:$D$20,"")="SI",E32=""),"Pedido",""),IF(AND(_xlfn.XLOOKUP($C$14,_Requeridos!$A$10:$A$20,_Requeridos!$E$10:$E$20,"")="SI",F32=""),"Descripción Activo SAP",""),IF(AND(_xlfn.XLOOKUP($C$14,_Requeridos!$A$10:$A$20,_Requeridos!$F$10:$F$20,"")="SI",G32=""),"Clase",""),IF(AND(_xlfn.XLOOKUP($C$14,_Requeridos!$A$10:$A$20,_Requeridos!$G$10:$G$20,"")="SI",H32=""),"Cantidad",""),IF(AND(_xlfn.XLOOKUP($C$14,_Requeridos!$A$10:$A$20,_Requeridos!$H$10:$H$20,"")="SI",I32=""),"Nombre principal AF",""),IF(AND(_xlfn.XLOOKUP($C$14,_Requeridos!$A$10:$A$20,_Requeridos!$I$10:$I$20,"")="SI",L32=""),"Fabricante",""),IF(AND(_xlfn.XLOOKUP($C$14,_Requeridos!$A$10:$A$20,_Requeridos!$J$10:$J$20,"")="SI",M32=""),"Nit Proveedor",""),IF(AND(_xlfn.XLOOKUP($C$14,_Requeridos!$A$10:$A$20,_Requeridos!$K$10:$K$20,"")="SI",N32=""),"Serie",""),IF(AND(_xlfn.XLOOKUP($C$14,_Requeridos!$A$10:$A$20,_Requeridos!$L$10:$L$20,"")="SI",P32=""),"Criterio Clas. 1",""),IF(AND(_xlfn.XLOOKUP($C$14,_Requeridos!$A$10:$A$20,_Requeridos!$M$10:$M$20,"")="SI",Q32=""),"Criterio Clas. 2",""),IF(AND(_xlfn.XLOOKUP($C$14,_Requeridos!$A$10:$A$20,_Requeridos!$N$10:$N$20,"")="SI",R32=""),"Criterio Clas. 3",""),IF(AND(_xlfn.XLOOKUP($C$14,_Requeridos!$A$10:$A$20,_Requeridos!$O$10:$O$20,"")="SI",S32=""),"Criterio Clas. 4",""),IF(AND(_xlfn.XLOOKUP($C$14,_Requeridos!$A$10:$A$20,_Requeridos!$P$10:$P$20,"")="SI",T32=""),"Criterio Clas. 5",""),IF(AND(_xlfn.XLOOKUP($C$14,_Requeridos!$A$10:$A$20,_Requeridos!$Q$10:$Q$20,"")="SI",U32=""),"Ubicación técnica",""),IF(AND(_xlfn.XLOOKUP($C$14,_Requeridos!$A$10:$A$20,_Requeridos!$R$10:$R$20,"")="SI",X32=""),"Centro",""),IF(AND(_xlfn.XLOOKUP($C$14,_Requeridos!$A$10:$A$20,_Requeridos!$S$10:$S$20,"")="SI",Y32=""),"Código País",""),IF(AND(_xlfn.XLOOKUP($C$14,_Requeridos!$A$10:$A$20,_Requeridos!$T$10:$T$20,"")="SI",Z32=""),"Emplazamiento",""),IF(AND(_xlfn.XLOOKUP($C$14,_Requeridos!$A$10:$A$20,_Requeridos!$U$10:$U$20,"")="SI",AB32=""),"Centro de Costo",""),IF(AND(_xlfn.XLOOKUP($C$14,_Requeridos!$A$10:$A$20,_Requeridos!$V$10:$V$20,"")="SI",AC32=""),"Número de personal",""),IF(AND(_xlfn.XLOOKUP($C$14,_Requeridos!$A$10:$A$20,_Requeridos!$W$10:$W$20,"")="SI",AH32=""),"Valor Unitario","")))>0,"⚠️ Faltan: "&_xlfn.TEXTJOIN(", ",TRUE,IF(AND(_xlfn.XLOOKUP($C$14,_Requeridos!$A$10:$A$20,_Requeridos!$B$10:$B$20,"")="SI",C32=""),"Orden de Inversión",""),IF(AND(_xlfn.XLOOKUP($C$14,_Requeridos!$A$10:$A$20,_Requeridos!$C$10:$C$20,"")="SI",D32=""),"Elemento PEP",""),IF(AND(_xlfn.XLOOKUP($C$14,_Requeridos!$A$10:$A$20,_Requeridos!$D$10:$D$20,"")="SI",E32=""),"Pedido",""),IF(AND(_xlfn.XLOOKUP($C$14,_Requeridos!$A$10:$A$20,_Requeridos!$E$10:$E$20,"")="SI",F32=""),"Descripción Activo SAP",""),IF(AND(_xlfn.XLOOKUP($C$14,_Requeridos!$A$10:$A$20,_Requeridos!$F$10:$F$20,"")="SI",G32=""),"Clase",""),IF(AND(_xlfn.XLOOKUP($C$14,_Requeridos!$A$10:$A$20,_Requeridos!$G$10:$G$20,"")="SI",H32=""),"Cantidad",""),IF(AND(_xlfn.XLOOKUP($C$14,_Requeridos!$A$10:$A$20,_Requeridos!$H$10:$H$20,"")="SI",I32=""),"Nombre principal AF",""),IF(AND(_xlfn.XLOOKUP($C$14,_Requeridos!$A$10:$A$20,_Requeridos!$I$10:$I$20,"")="SI",L32=""),"Fabricante",""),IF(AND(_xlfn.XLOOKUP($C$14,_Requeridos!$A$10:$A$20,_Requeridos!$J$10:$J$20,"")="SI",M32=""),"Nit Proveedor",""),IF(AND(_xlfn.XLOOKUP($C$14,_Requeridos!$A$10:$A$20,_Requeridos!$K$10:$K$20,"")="SI",N32=""),"Serie",""),IF(AND(_xlfn.XLOOKUP($C$14,_Requeridos!$A$10:$A$20,_Requeridos!$L$10:$L$20,"")="SI",P32=""),"Criterio Clas. 1",""),IF(AND(_xlfn.XLOOKUP($C$14,_Requeridos!$A$10:$A$20,_Requeridos!$M$10:$M$20,"")="SI",Q32=""),"Criterio Clas. 2",""),IF(AND(_xlfn.XLOOKUP($C$14,_Requeridos!$A$10:$A$20,_Requeridos!$N$10:$N$20,"")="SI",R32=""),"Criterio Clas. 3",""),IF(AND(_xlfn.XLOOKUP($C$14,_Requeridos!$A$10:$A$20,_Requeridos!$O$10:$O$20,"")="SI",S32=""),"Criterio Clas. 4",""),IF(AND(_xlfn.XLOOKUP($C$14,_Requeridos!$A$10:$A$20,_Requeridos!$P$10:$P$20,"")="SI",T32=""),"Criterio Clas. 5",""),IF(AND(_xlfn.XLOOKUP($C$14,_Requeridos!$A$10:$A$20,_Requeridos!$Q$10:$Q$20,"")="SI",U32=""),"Ubicación técnica",""),IF(AND(_xlfn.XLOOKUP($C$14,_Requeridos!$A$10:$A$20,_Requeridos!$R$10:$R$20,"")="SI",X32=""),"Centro",""),IF(AND(_xlfn.XLOOKUP($C$14,_Requeridos!$A$10:$A$20,_Requeridos!$S$10:$S$20,"")="SI",Y32=""),"Código País",""),IF(AND(_xlfn.XLOOKUP($C$14,_Requeridos!$A$10:$A$20,_Requeridos!$T$10:$T$20,"")="SI",Z32=""),"Emplazamiento",""),IF(AND(_xlfn.XLOOKUP($C$14,_Requeridos!$A$10:$A$20,_Requeridos!$U$10:$U$20,"")="SI",AB32=""),"Centro de Costo",""),IF(AND(_xlfn.XLOOKUP($C$14,_Requeridos!$A$10:$A$20,_Requeridos!$V$10:$V$20,"")="SI",AC32=""),"Número de personal",""),IF(AND(_xlfn.XLOOKUP($C$14,_Requeridos!$A$10:$A$20,_Requeridos!$W$10:$W$20,"")="SI",AH32=""),"Valor Unitario","")),"✅ Completo"))
B33: 12 | G33: =IFERROR(_xlfn.XLOOKUP(F33,Clase!$C$2:$C$292,Clase!$B$2:$B$292,""),"") | AD33: =IFERROR(_xlfn.XLOOKUP(AB33,Ceco!$B$2:$B$901,Ceco!$C$2:$C$901,""),"") | AJ33: =IF(COUNTA(C33,D33,E33,F33,H33,I33,L33,M33,N33,P33,Q33,R33,S33,T33,U33,X33,Y33,Z33,AB33,AC33,AH33)=0,"",IF(LEN(_xlfn.TEXTJOIN(", ",TRUE,IF(AND(_xlfn.XLOOKUP($C$14,_Requeridos!$A$10:$A$20,_Requeridos!$B$10:$B$20,"")="SI",C33=""),"Orden de Inversión",""),IF(AND(_xlfn.XLOOKUP($C$14,_Requeridos!$A$10:$A$20,_Requeridos!$C$10:$C$20,"")="SI",D33=""),"Elemento PEP",""),IF(AND(_xlfn.XLOOKUP($C$14,_Requeridos!$A$10:$A$20,_Requeridos!$D$10:$D$20,"")="SI",E33=""),"Pedido",""),IF(AND(_xlfn.XLOOKUP($C$14,_Requeridos!$A$10:$A$20,_Requeridos!$E$10:$E$20,"")="SI",F33=""),"Descripción Activo SAP",""),IF(AND(_xlfn.XLOOKUP($C$14,_Requeridos!$A$10:$A$20,_Requeridos!$F$10:$F$20,"")="SI",G33=""),"Clase",""),IF(AND(_xlfn.XLOOKUP($C$14,_Requeridos!$A$10:$A$20,_Requeridos!$G$10:$G$20,"")="SI",H33=""),"Cantidad",""),IF(AND(_xlfn.XLOOKUP($C$14,_Requeridos!$A$10:$A$20,_Requeridos!$H$10:$H$20,"")="SI",I33=""),"Nombre principal AF",""),IF(AND(_xlfn.XLOOKUP($C$14,_Requeridos!$A$10:$A$20,_Requeridos!$I$10:$I$20,"")="SI",L33=""),"Fabricante",""),IF(AND(_xlfn.XLOOKUP($C$14,_Requeridos!$A$10:$A$20,_Requeridos!$J$10:$J$20,"")="SI",M33=""),"Nit Proveedor",""),IF(AND(_xlfn.XLOOKUP($C$14,_Requeridos!$A$10:$A$20,_Requeridos!$K$10:$K$20,"")="SI",N33=""),"Serie",""),IF(AND(_xlfn.XLOOKUP($C$14,_Requeridos!$A$10:$A$20,_Requeridos!$L$10:$L$20,"")="SI",P33=""),"Criterio Clas. 1",""),IF(AND(_xlfn.XLOOKUP($C$14,_Requeridos!$A$10:$A$20,_Requeridos!$M$10:$M$20,"")="SI",Q33=""),"Criterio Clas. 2",""),IF(AND(_xlfn.XLOOKUP($C$14,_Requeridos!$A$10:$A$20,_Requeridos!$N$10:$N$20,"")="SI",R33=""),"Criterio Clas. 3",""),IF(AND(_xlfn.XLOOKUP($C$14,_Requeridos!$A$10:$A$20,_Requeridos!$O$10:$O$20,"")="SI",S33=""),"Criterio Clas. 4",""),IF(AND(_xlfn.XLOOKUP($C$14,_Requeridos!$A$10:$A$20,_Requeridos!$P$10:$P$20,"")="SI",T33=""),"Criterio Clas. 5",""),IF(AND(_xlfn.XLOOKUP($C$14,_Requeridos!$A$10:$A$20,_Requeridos!$Q$10:$Q$20,"")="SI",U33=""),"Ubicación técnica",""),IF(AND(_xlfn.XLOOKUP($C$14,_Requeridos!$A$10:$A$20,_Requeridos!$R$10:$R$20,"")="SI",X33=""),"Centro",""),IF(AND(_xlfn.XLOOKUP($C$14,_Requeridos!$A$10:$A$20,_Requeridos!$S$10:$S$20,"")="SI",Y33=""),"Código País",""),IF(AND(_xlfn.XLOOKUP($C$14,_Requeridos!$A$10:$A$20,_Requeridos!$T$10:$T$20,"")="SI",Z33=""),"Emplazamiento",""),IF(AND(_xlfn.XLOOKUP($C$14,_Requeridos!$A$10:$A$20,_Requeridos!$U$10:$U$20,"")="SI",AB33=""),"Centro de Costo",""),IF(AND(_xlfn.XLOOKUP($C$14,_Requeridos!$A$10:$A$20,_Requeridos!$V$10:$V$20,"")="SI",AC33=""),"Número de personal",""),IF(AND(_xlfn.XLOOKUP($C$14,_Requeridos!$A$10:$A$20,_Requeridos!$W$10:$W$20,"")="SI",AH33=""),"Valor Unitario","")))>0,"⚠️ Faltan: "&_xlfn.TEXTJOIN(", ",TRUE,IF(AND(_xlfn.XLOOKUP($C$14,_Requeridos!$A$10:$A$20,_Requeridos!$B$10:$B$20,"")="SI",C33=""),"Orden de Inversión",""),IF(AND(_xlfn.XLOOKUP($C$14,_Requeridos!$A$10:$A$20,_Requeridos!$C$10:$C$20,"")="SI",D33=""),"Elemento PEP",""),IF(AND(_xlfn.XLOOKUP($C$14,_Requeridos!$A$10:$A$20,_Requeridos!$D$10:$D$20,"")="SI",E33=""),"Pedido",""),IF(AND(_xlfn.XLOOKUP($C$14,_Requeridos!$A$10:$A$20,_Requeridos!$E$10:$E$20,"")="SI",F33=""),"Descripción Activo SAP",""),IF(AND(_xlfn.XLOOKUP($C$14,_Requeridos!$A$10:$A$20,_Requeridos!$F$10:$F$20,"")="SI",G33=""),"Clase",""),IF(AND(_xlfn.XLOOKUP($C$14,_Requeridos!$A$10:$A$20,_Requeridos!$G$10:$G$20,"")="SI",H33=""),"Cantidad",""),IF(AND(_xlfn.XLOOKUP($C$14,_Requeridos!$A$10:$A$20,_Requeridos!$H$10:$H$20,"")="SI",I33=""),"Nombre principal AF",""),IF(AND(_xlfn.XLOOKUP($C$14,_Requeridos!$A$10:$A$20,_Requeridos!$I$10:$I$20,"")="SI",L33=""),"Fabricante",""),IF(AND(_xlfn.XLOOKUP($C$14,_Requeridos!$A$10:$A$20,_Requeridos!$J$10:$J$20,"")="SI",M33=""),"Nit Proveedor",""),IF(AND(_xlfn.XLOOKUP($C$14,_Requeridos!$A$10:$A$20,_Requeridos!$K$10:$K$20,"")="SI",N33=""),"Serie",""),IF(AND(_xlfn.XLOOKUP($C$14,_Requeridos!$A$10:$A$20,_Requeridos!$L$10:$L$20,"")="SI",P33=""),"Criterio Clas. 1",""),IF(AND(_xlfn.XLOOKUP($C$14,_Requeridos!$A$10:$A$20,_Requeridos!$M$10:$M$20,"")="SI",Q33=""),"Criterio Clas. 2",""),IF(AND(_xlfn.XLOOKUP($C$14,_Requeridos!$A$10:$A$20,_Requeridos!$N$10:$N$20,"")="SI",R33=""),"Criterio Clas. 3",""),IF(AND(_xlfn.XLOOKUP($C$14,_Requeridos!$A$10:$A$20,_Requeridos!$O$10:$O$20,"")="SI",S33=""),"Criterio Clas. 4",""),IF(AND(_xlfn.XLOOKUP($C$14,_Requeridos!$A$10:$A$20,_Requeridos!$P$10:$P$20,"")="SI",T33=""),"Criterio Clas. 5",""),IF(AND(_xlfn.XLOOKUP($C$14,_Requeridos!$A$10:$A$20,_Requeridos!$Q$10:$Q$20,"")="SI",U33=""),"Ubicación técnica",""),IF(AND(_xlfn.XLOOKUP($C$14,_Requeridos!$A$10:$A$20,_Requeridos!$R$10:$R$20,"")="SI",X33=""),"Centro",""),IF(AND(_xlfn.XLOOKUP($C$14,_Requeridos!$A$10:$A$20,_Requeridos!$S$10:$S$20,"")="SI",Y33=""),"Código País",""),IF(AND(_xlfn.XLOOKUP($C$14,_Requeridos!$A$10:$A$20,_Requeridos!$T$10:$T$20,"")="SI",Z33=""),"Emplazamiento",""),IF(AND(_xlfn.XLOOKUP($C$14,_Requeridos!$A$10:$A$20,_Requeridos!$U$10:$U$20,"")="SI",AB33=""),"Centro de Costo",""),IF(AND(_xlfn.XLOOKUP($C$14,_Requeridos!$A$10:$A$20,_Requeridos!$V$10:$V$20,"")="SI",AC33=""),"Número de personal",""),IF(AND(_xlfn.XLOOKUP($C$14,_Requeridos!$A$10:$A$20,_Requeridos!$W$10:$W$20,"")="SI",AH33=""),"Valor Unitario","")),"✅ Completo"))
B34: 13 | G34: =IFERROR(_xlfn.XLOOKUP(F34,Clase!$C$2:$C$292,Clase!$B$2:$B$292,""),"") | AD34: =IFERROR(_xlfn.XLOOKUP(AB34,Ceco!$B$2:$B$901,Ceco!$C$2:$C$901,""),"") | AJ34: =IF(COUNTA(C34,D34,E34,F34,H34,I34,L34,M34,N34,P34,Q34,R34,S34,T34,U34,X34,Y34,Z34,AB34,AC34,AH34)=0,"",IF(LEN(_xlfn.TEXTJOIN(", ",TRUE,IF(AND(_xlfn.XLOOKUP($C$14,_Requeridos!$A$10:$A$20,_Requeridos!$B$10:$B$20,"")="SI",C34=""),"Orden de Inversión",""),IF(AND(_xlfn.XLOOKUP($C$14,_Requeridos!$A$10:$A$20,_Requeridos!$C$10:$C$20,"")="SI",D34=""),"Elemento PEP",""),IF(AND(_xlfn.XLOOKUP($C$14,_Requeridos!$A$10:$A$20,_Requeridos!$D$10:$D$20,"")="SI",E34=""),"Pedido",""),IF(AND(_xlfn.XLOOKUP($C$14,_Requeridos!$A$10:$A$20,_Requeridos!$E$10:$E$20,"")="SI",F34=""),"Descripción Activo SAP",""),IF(AND(_xlfn.XLOOKUP($C$14,_Requeridos!$A$10:$A$20,_Requeridos!$F$10:$F$20,"")="SI",G34=""),"Clase",""),IF(AND(_xlfn.XLOOKUP($C$14,_Requeridos!$A$10:$A$20,_Requeridos!$G$10:$G$20,"")="SI",H34=""),"Cantidad",""),IF(AND(_xlfn.XLOOKUP($C$14,_Requeridos!$A$10:$A$20,_Requeridos!$H$10:$H$20,"")="SI",I34=""),"Nombre principal AF",""),IF(AND(_xlfn.XLOOKUP($C$14,_Requeridos!$A$10:$A$20,_Requeridos!$I$10:$I$20,"")="SI",L34=""),"Fabricante",""),IF(AND(_xlfn.XLOOKUP($C$14,_Requeridos!$A$10:$A$20,_Requeridos!$J$10:$J$20,"")="SI",M34=""),"Nit Proveedor",""),IF(AND(_xlfn.XLOOKUP($C$14,_Requeridos!$A$10:$A$20,_Requeridos!$K$10:$K$20,"")="SI",N34=""),"Serie",""),IF(AND(_xlfn.XLOOKUP($C$14,_Requeridos!$A$10:$A$20,_Requeridos!$L$10:$L$20,"")="SI",P34=""),"Criterio Clas. 1",""),IF(AND(_xlfn.XLOOKUP($C$14,_Requeridos!$A$10:$A$20,_Requeridos!$M$10:$M$20,"")="SI",Q34=""),"Criterio Clas. 2",""),IF(AND(_xlfn.XLOOKUP($C$14,_Requeridos!$A$10:$A$20,_Requeridos!$N$10:$N$20,"")="SI",R34=""),"Criterio Clas. 3",""),IF(AND(_xlfn.XLOOKUP($C$14,_Requeridos!$A$10:$A$20,_Requeridos!$O$10:$O$20,"")="SI",S34=""),"Criterio Clas. 4",""),IF(AND(_xlfn.XLOOKUP($C$14,_Requeridos!$A$10:$A$20,_Requeridos!$P$10:$P$20,"")="SI",T34=""),"Criterio Clas. 5",""),IF(AND(_xlfn.XLOOKUP($C$14,_Requeridos!$A$10:$A$20,_Requeridos!$Q$10:$Q$20,"")="SI",U34=""),"Ubicación técnica",""),IF(AND(_xlfn.XLOOKUP($C$14,_Requeridos!$A$10:$A$20,_Requeridos!$R$10:$R$20,"")="SI",X34=""),"Centro",""),IF(AND(_xlfn.XLOOKUP($C$14,_Requeridos!$A$10:$A$20,_Requeridos!$S$10:$S$20,"")="SI",Y34=""),"Código País",""),IF(AND(_xlfn.XLOOKUP($C$14,_Requeridos!$A$10:$A$20,_Requeridos!$T$10:$T$20,"")="SI",Z34=""),"Emplazamiento",""),IF(AND(_xlfn.XLOOKUP($C$14,_Requeridos!$A$10:$A$20,_Requeridos!$U$10:$U$20,"")="SI",AB34=""),"Centro de Costo",""),IF(AND(_xlfn.XLOOKUP($C$14,_Requeridos!$A$10:$A$20,_Requeridos!$V$10:$V$20,"")="SI",AC34=""),"Número de personal",""),IF(AND(_xlfn.XLOOKUP($C$14,_Requeridos!$A$10:$A$20,_Requeridos!$W$10:$W$20,"")="SI",AH34=""),"Valor Unitario","")))>0,"⚠️ Faltan: "&_xlfn.TEXTJOIN(", ",TRUE,IF(AND(_xlfn.XLOOKUP($C$14,_Requeridos!$A$10:$A$20,_Requeridos!$B$10:$B$20,"")="SI",C34=""),"Orden de Inversión",""),IF(AND(_xlfn.XLOOKUP($C$14,_Requeridos!$A$10:$A$20,_Requeridos!$C$10:$C$20,"")="SI",D34=""),"Elemento PEP",""),IF(AND(_xlfn.XLOOKUP($C$14,_Requeridos!$A$10:$A$20,_Requeridos!$D$10:$D$20,"")="SI",E34=""),"Pedido",""),IF(AND(_xlfn.XLOOKUP($C$14,_Requeridos!$A$10:$A$20,_Requeridos!$E$10:$E$20,"")="SI",F34=""),"Descripción Activo SAP",""),IF(AND(_xlfn.XLOOKUP($C$14,_Requeridos!$A$10:$A$20,_Requeridos!$F$10:$F$20,"")="SI",G34=""),"Clase",""),IF(AND(_xlfn.XLOOKUP($C$14,_Requeridos!$A$10:$A$20,_Requeridos!$G$10:$G$20,"")="SI",H34=""),"Cantidad",""),IF(AND(_xlfn.XLOOKUP($C$14,_Requeridos!$A$10:$A$20,_Requeridos!$H$10:$H$20,"")="SI",I34=""),"Nombre principal AF",""),IF(AND(_xlfn.XLOOKUP($C$14,_Requeridos!$A$10:$A$20,_Requeridos!$I$10:$I$20,"")="SI",L34=""),"Fabricante",""),IF(AND(_xlfn.XLOOKUP($C$14,_Requeridos!$A$10:$A$20,_Requeridos!$J$10:$J$20,"")="SI",M34=""),"Nit Proveedor",""),IF(AND(_xlfn.XLOOKUP($C$14,_Requeridos!$A$10:$A$20,_Requeridos!$K$10:$K$20,"")="SI",N34=""),"Serie",""),IF(AND(_xlfn.XLOOKUP($C$14,_Requeridos!$A$10:$A$20,_Requeridos!$L$10:$L$20,"")="SI",P34=""),"Criterio Clas. 1",""),IF(AND(_xlfn.XLOOKUP($C$14,_Requeridos!$A$10:$A$20,_Requeridos!$M$10:$M$20,"")="SI",Q34=""),"Criterio Clas. 2",""),IF(AND(_xlfn.XLOOKUP($C$14,_Requeridos!$A$10:$A$20,_Requeridos!$N$10:$N$20,"")="SI",R34=""),"Criterio Clas. 3",""),IF(AND(_xlfn.XLOOKUP($C$14,_Requeridos!$A$10:$A$20,_Requeridos!$O$10:$O$20,"")="SI",S34=""),"Criterio Clas. 4",""),IF(AND(_xlfn.XLOOKUP($C$14,_Requeridos!$A$10:$A$20,_Requeridos!$P$10:$P$20,"")="SI",T34=""),"Criterio Clas. 5",""),IF(AND(_xlfn.XLOOKUP($C$14,_Requeridos!$A$10:$A$20,_Requeridos!$Q$10:$Q$20,"")="SI",U34=""),"Ubicación técnica",""),IF(AND(_xlfn.XLOOKUP($C$14,_Requeridos!$A$10:$A$20,_Requeridos!$R$10:$R$20,"")="SI",X34=""),"Centro",""),IF(AND(_xlfn.XLOOKUP($C$14,_Requeridos!$A$10:$A$20,_Requeridos!$S$10:$S$20,"")="SI",Y34=""),"Código País",""),IF(AND(_xlfn.XLOOKUP($C$14,_Requeridos!$A$10:$A$20,_Requeridos!$T$10:$T$20,"")="SI",Z34=""),"Emplazamiento",""),IF(AND(_xlfn.XLOOKUP($C$14,_Requeridos!$A$10:$A$20,_Requeridos!$U$10:$U$20,"")="SI",AB34=""),"Centro de Costo",""),IF(AND(_xlfn.XLOOKUP($C$14,_Requeridos!$A$10:$A$20,_Requeridos!$V$10:$V$20,"")="SI",AC34=""),"Número de personal",""),IF(AND(_xlfn.XLOOKUP($C$14,_Requeridos!$A$10:$A$20,_Requeridos!$W$10:$W$20,"")="SI",AH34=""),"Valor Unitario","")),"✅ Completo"))
... B87: 66 | G87: =IFERROR(_xlfn.XLOOKUP(F87,Clase!$C$2:$C$292,Clase!$B$2:$B$292,""),"") | AD87: =IFERROR(_xlfn.XLOOKUP(AB87,Ceco!$B$2:$B$901,Ceco!$C$2:$C$901,""),"") | AJ87: =IF(COUNTA(C87,D87,E87,F87,H87,I87,L87,M87,N87,P87,Q87,R87,S87,T87,U87,X87,Y87,Z87,AB87,AC87,AH87)=0,"",IF(LEN(_xlfn.TEXTJOIN(", ",TRUE,IF(AND(_xlfn.XLOOKUP($C$14,_Requeridos!$A$10:$A$20,_Requeridos!$B$10:$B$20,"")="SI",C87=""),"Orden de Inversión",""),IF(AND(_xlfn.XLOOKUP($C$14,_Requeridos!$A$10:$A$20,_Requeridos!$C$10:$C$20,"")="SI",D87=""),"Elemento PEP",""),IF(AND(_xlfn.XLOOKUP($C$14,_Requeridos!$A$10:$A$20,_Requeridos!$D$10:$D$20,"")="SI",E87=""),"Pedido",""),IF(AND(_xlfn.XLOOKUP($C$14,_Requeridos!$A$10:$A$20,_Requeridos!$E$10:$E$20,"")="SI",F87=""),"Descripción Activo SAP",""),IF(AND(_xlfn.XLOOKUP($C$14,_Requeridos!$A$10:$A$20,_Requeridos!$F$10:$F$20,"")="SI",G87=""),"Clase",""),IF(AND(_xlfn.XLOOKUP($C$14,_Requeridos!$A$10:$A$20,_Requeridos!$G$10:$G$20,"")="SI",H87=""),"Cantidad",""),IF(AND(_xlfn.XLOOKUP($C$14,_Requeridos!$A$10:$A$20,_Requeridos!$H$10:$H$20,"")="SI",I87=""),"Nombre principal AF",""),IF(AND(_xlfn.XLOOKUP($C$14,_Requeridos!$A$10:$A$20,_Requeridos!$I$10:$I$20,"")="SI",L87=""),"Fabricante",""),IF(AND(_xlfn.XLOOKUP($C$14,_Requeridos!$A$10:$A$20,_Requeridos!$J$10:$J$20,"")="SI",M87=""),"Nit Proveedor",""),IF(AND(_xlfn.XLOOKUP($C$14,_Requeridos!$A$10:$A$20,_Requeridos!$K$10:$K$20,"")="SI",N87=""),"Serie",""),IF(AND(_xlfn.XLOOKUP($C$14,_Requeridos!$A$10:$A$20,_Requeridos!$L$10:$L$20,"")="SI",P87=""),"Criterio Clas. 1",""),IF(AND(_xlfn.XLOOKUP($C$14,_Requeridos!$A$10:$A$20,_Requeridos!$M$10:$M$20,"")="SI",Q87=""),"Criterio Clas. 2",""),IF(AND(_xlfn.XLOOKUP($C$14,_Requeridos!$A$10:$A$20,_Requeridos!$N$10:$N$20,"")="SI",R87=""),"Criterio Clas. 3",""),IF(AND(_xlfn.XLOOKUP($C$14,_Requeridos!$A$10:$A$20,_Requeridos!$O$10:$O$20,"")="SI",S87=""),"Criterio Clas. 4",""),IF(AND(_xlfn.XLOOKUP($C$14,_Requeridos!$A$10:$A$20,_Requeridos!$P$10:$P$20,"")="SI",T87=""),"Criterio Clas. 5",""),IF(AND(_xlfn.XLOOKUP($C$14,_Requeridos!$A$10:$A$20,_Requeridos!$Q$10:$Q$20,"")="SI",U87=""),"Ubicación técnica",""),IF(AND(_xlfn.XLOOKUP($C$14,_Requeridos!$A$10:$A$20,_Requeridos!$R$10:$R$20,"")="SI",X87=""),"Centro",""),IF(AND(_xlfn.XLOOKUP($C$14,_Requeridos!$A$10:$A$20,_Requeridos!$S$10:$S$20,"")="SI",Y87=""),"Código País",""),IF(AND(_xlfn.XLOOKUP($C$14,_Requeridos!$A$10:$A$20,_Requeridos!$T$10:$T$20,"")="SI",Z87=""),"Emplazamiento",""),IF(AND(_xlfn.XLOOKUP($C$14,_Requeridos!$A$10:$A$20,_Requeridos!$U$10:$U$20,"")="SI",AB87=""),"Centro de Costo",""),IF(AND(_xlfn.XLOOKUP($C$14,_Requeridos!$A$10:$A$20,_Requeridos!$V$10:$V$20,"")="SI",AC87=""),"Número de personal",""),IF(AND(_xlfn.XLOOKUP($C$14,_Requeridos!$A$10:$A$20,_Requeridos!$W$10:$W$20,"")="SI",AH87=""),"Valor Unitario","")))>0,"⚠️ Faltan: "&_xlfn.TEXTJOIN(", ",TRUE,IF(AND(_xlfn.XLOOKUP($C$14,_Requeridos!$A$10:$A$20,_Requeridos!$B$10:$B$20,"")="SI",C87=""),"Orden de Inversión",""),IF(AND(_xlfn.XLOOKUP($C$14,_Requeridos!$A$10:$A$20,_Requeridos!$C$10:$C$20,"")="SI",D87=""),"Elemento PEP",""),IF(AND(_xlfn.XLOOKUP($C$14,_Requeridos!$A$10:$A$20,_Requeridos!$D$10:$D$20,"")="SI",E87=""),"Pedido",""),IF(AND(_xlfn.XLOOKUP($C$14,_Requeridos!$A$10:$A$20,_Requeridos!$E$10:$E$20,"")="SI",F87=""),"Descripción Activo SAP",""),IF(AND(_xlfn.XLOOKUP($C$14,_Requeridos!$A$10:$A$20,_Requeridos!$F$10:$F$20,"")="SI",G87=""),"Clase",""),IF(AND(_xlfn.XLOOKUP($C$14,_Requeridos!$A$10:$A$20,_Requeridos!$G$10:$G$20,"")="SI",H87=""),"Cantidad",""),IF(AND(_xlfn.XLOOKUP($C$14,_Requeridos!$A$10:$A$20,_Requeridos!$H$10:$H$20,"")="SI",I87=""),"Nombre principal AF",""),IF(AND(_xlfn.XLOOKUP($C$14,_Requeridos!$A$10:$A$20,_Requeridos!$I$10:$I$20,"")="SI",L87=""),"Fabricante",""),IF(AND(_xlfn.XLOOKUP($C$14,_Requeridos!$A$10:$A$20,_Requeridos!$J$10:$J$20,"")="SI",M87=""),"Nit Proveedor",""),IF(AND(_xlfn.XLOOKUP($C$14,_Requeridos!$A$10:$A$20,_Requeridos!$K$10:$K$20,"")="SI",N87=""),"Serie",""),IF(AND(_xlfn.XLOOKUP($C$14,_Requeridos!$A$10:$A$20,_Requeridos!$L$10:$L$20,"")="SI",P87=""),"Criterio Clas. 1",""),IF(AND(_xlfn.XLOOKUP($C$14,_Requeridos!$A$10:$A$20,_Requeridos!$M$10:$M$20,"")="SI",Q87=""),"Criterio Clas. 2",""),IF(AND(_xlfn.XLOOKUP($C$14,_Requeridos!$A$10:$A$20,_Requeridos!$N$10:$N$20,"")="SI",R87=""),"Criterio Clas. 3",""),IF(AND(_xlfn.XLOOKUP($C$14,_Requeridos!$A$10:$A$20,_Requeridos!$O$10:$O$20,"")="SI",S87=""),"Criterio Clas. 4",""),IF(AND(_xlfn.XLOOKUP($C$14,_Requeridos!$A$10:$A$20,_Requeridos!$P$10:$P$20,"")="SI",T87=""),"Criterio Clas. 5",""),IF(AND(_xlfn.XLOOKUP($C$14,_Requeridos!$A$10:$A$20,_Requeridos!$Q$10:$Q$20,"")="SI",U87=""),"Ubicación técnica",""),IF(AND(_xlfn.XLOOKUP($C$14,_Requeridos!$A$10:$A$20,_Requeridos!$R$10:$R$20,"")="SI",X87=""),"Centro",""),IF(AND(_xlfn.XLOOKUP($C$14,_Requeridos!$A$10:$A$20,_Requeridos!$S$10:$S$20,"")="SI",Y87=""),"Código País",""),IF(AND(_xlfn.XLOOKUP($C$14,_Requeridos!$A$10:$A$20,_Requeridos!$T$10:$T$20,"")="SI",Z87=""),"Emplazamiento",""),IF(AND(_xlfn.XLOOKUP($C$14,_Requeridos!$A$10:$A$20,_Requeridos!$U$10:$U$20,"")="SI",AB87=""),"Centro de Costo",""),IF(AND(_xlfn.XLOOKUP($C$14,_Requeridos!$A$10:$A$20,_Requeridos!$V$10:$V$20,"")="SI",AC87=""),"Número de personal",""),IF(AND(_xlfn.XLOOKUP($C$14,_Requeridos!$A$10:$A$20,_Requeridos!$W$10:$W$20,"")="SI",AH87=""),"Valor Unitario","")),"✅ Completo"))
B88: 67
B89: 68

Sheet LSMW 
A1: Clase AF (ANLKL) | B1: Sociedad (BUKRS) | C1: Cantidad AF iguales (NASSETS) | D1: Postcapitalización de un inmov. (XNACH) | E1: Denominación del activo fijo (TXT50) | F1: Denominación del activo fijo (cont.) (TXA50) | G1: Texto número principal AF (ANLHTXT) | H1: Número de serie (SERNR) | I1: Número de inventario (INVNR) | J1: Cantidad (MENGE) | K1: Unidad de medida base (MEINS) | L1: Se gestiona históricamente el AF (XHIST) | M1: Fecha del último inventario (IVDAT) | N1: Indicador de inventario (INKEN) | O1: Datos adicionales de inventario (INVZU) | P1: Fecha de capitalización del activo fijo (AKTIV) | Q1: Serial (ZZSERNR) | R1: Elemento PEP: Proyecto de inv. (ZZPOSNR) | S1: División (GSBER) | T1: Centro de coste (KOSTL) | U1: CeCo responsable del activo fijo (KOSTLV) | V1: Clase de actividad (LSTAR) | W1: Centro (WERKS) | X1: Ord.costes (CAUFN) | Y1: Orden mantenimiento (IAUFN) | Z1: Emplazamiento del activo fijo (STORT) | AA1: Local (RAUMN) | AB1: Matrícula de vehículo (KFZKZ) | AC1: Número de personal (PERNR) | AD1: Factor de turnos (MSFAK) | AE1: Fondo (GEBER) | AF1: Área Funcional (FKBER) | AG1: Centro gestor (FISTL) | AH1: Ubicación técnica (ZZTPLNR) | AI1: Unidad Generadora Efectivo (ZZUNDGENEFEC) | AJ1: Criterio de clasificación 1 (ORD41) | AK1: Criterio de clasificación 2 (ORD42) | AL1: Criterio de clasificación 3 (ORD43) | AM1: Criterio de clasificación 4 (ORD44) | AN1: Criterio de clasificación 5 (GDLGRP) | AO1: Destino de la inversión (IZWEK) | AP1: Supranúmero de activo fijo (ANLUE) | AQ1: Cantidad de equipos (EQANZ) | AR1: Acreedor (otra palabra clave) (LIFNR) | AS1: Fabricante del activo fijo (HERST) | AT1: Indicador: El AF comprado nuevo (XNEU_AM) | AU1: Indicador: AF comprado de 2° mano (XGBR_AM) | AV1: País de origen del activo fijo (LAND1) | AW1: Denominación de tipo(TYPBZ) | AX1: Orden de inversión (EAUFN) | AY1: Elemento PEP: Proyecto de inversión (POSNR)
A2: =Formato!G22 -> A451217 | B2: =Formato!C14 -> ISA | C2: =Formato!H22 -> 1 | E2: =Formato!I22 -> Controlador campo - Prueba 100 | F2: =Formato!J22 -> Controlador campo - Prueba 3 | G2: =Formato!K22 -> Controlador campo - Prueba 3 | H2: =Formato!N22 -> BM2501019994 | I2: =IF(Formato!AA22="","",Formato!AA22) | J2: 1 | K2: un | Q2: =Formato!N22 -> BM2501019994 | R2: =Formato!D22 -> RI-POAS1-1.2.02 | S2: 3208 | T2: =Formato!AB22 -> 10004 | U2: =Formato!AD22 -> 10004 | W2: =Formato!X22 -> Tran | X2: =IF(Formato!C22="","",Formato!C22) | Z2: 05649 | AB2: =Formato!W22 -> 4510014034 | AJ2: =IF(Formato!P22="","",Formato!P22) | AK2: =IF(Formato!Q22="","",Formato!Q22) | AL2: =Formato!R22 -> IC03 | AM2: =IF(Formato!S22="","",Formato!S22) | AN2: =Formato!T22 -> P003S009 | AR2: =IF(Formato!M22="","",Formato!M22) | AS2: =Formato!L22 -> SIEMENS | AV2: =IF(Formato!Y22="","",Formato!Y22) | AW2: =IF(Formato!O22="","",Formato!O22) | AX2: =IF(Formato!C22="","",Formato!C22) | AY2: =Formato!D22 -> RI-POAS1-1.2.02
